Workbook

Sheet Final_Cleaned_Data_V2
B1: (Clean this out prior to datathon) | J1: 1 | L1: 2 | M1: 3 | O1: 4 | P1: 5 | Q1: 6 | R1: 7 | S1: 8 | T1: 9
A2: Unnamed: 0 | B2: text | C2: url | D2: name | E2: department | F2: text_len | G2: too_long_flag | H2: Volunteer ID | I2: Progress | J2: Text Type | L2: Incident Mentioned | M2: Incident Type | O2: Difficulty to extract incident type | P2: Officers Perpetrating Incident | Q2: Officer Gender | R2: Officer Race | S2: Complainant Gender | T2: Complainant Race | U2: Location Found | V2: Location (if found) | W2: Difficulty of Finding Location | X2: Date (leave blank if unknown) | Y2: Time
A3: 82 | B3: UNITED STATES DISTRICT COURT DISTRICT OF MINNESOTA Luis Daniel Garcia, Plaintiff, vs. Blayne Lehner, in his individual capacity as an officer of the City of Minneapolis, and the City of Minneapolis, Defendants. FILE NO. 15-cv-3214 (SRN/HB) ORDER Pursuant to the stipulation of the Plaintiff and the City of Minneapolis [Doc. No. 28], all claims against the City of Minneapolis are hereby dismissed with prejudice and without costs to either party. Dated: July 20, 2016 s/Susan Richard Nelson SUSAN RICHARD NELSON United States District Judge CASE 0:15-cv-03214-SRN-HB Document 29 Filed 07/20/16 Page 1 of 1 | C3: ['https://d3n8a8pro7vhmx.cloudfront.net/cuapb/pages/270/attachments/original/1614138451/Document_29_Order_of_Dismissal.pdf?1614138451'] | D3: ['Blayne Lehner, badge #4073'] | E3: ['Department:Minneapolis Police Department'] | F3: 698 | K3: =IF(Final_Cleaned_Data_V2!J3="Other", "Please specify here", "") | N3: =IF(Final_Cleaned_Data_V2!M3="Other", "Please specify here", "")
A4: 83 | B4: Too_Long:Over 20 Pages OPCR Case #13-069Lel Lee PANEL RECOMMENDATION Page 2 of 4 Allegations 2. Inappropriate Language: That Officer Golgart used inappropriate language "You're an alcoholic." OPCR Case #13-069Lel Lee PANEL RECOMMENDATION Page 4 of 4 Allegation #2: Inappropriate Language Supportive Findings: YES NO REMAND SPLIT This allegation has merit. This allegation does not have merit. Remand to investigation for additional information. There is no majority vote. The panel unanimously finds there is sufficient evidence to find merit in this allegation. DH | C4: ['https://d3n8a8pro7vhmx.cloudfront.net/cuapb/pages/270/attachments/original/1581994153/OPCR_13-069_Part_1.pdf?1581994153'] | D4: ['James Golgart, Jr., badge #2317'] | E4: ['Department:Minneapolis Police Department'] | F4: 711 | G4: TRUE | K4: =IF(Final_Cleaned_Data_V2!J4="Other", "Please specify here", "") | N4: =IF(Final_Cleaned_Data_V2!M4="Other", "Please specify here", "")
A5: 84 | B5: PUBLIC INFORMATION - EMPLOYEE SUMMARY SAINT PAUL POLICE DEPARTMENT INTERNAL AFFAIRS UNIT Employee Name: HALLSTROM, KURTIS W. Employee ID: 253400 From: January 01, 1900 to October 05, 2022 IA Number: 00-0116 STATUS: Completed Complainant: Diperna, Nancy IA Number: 01-0506 STATUS: Completed Complainant: Attorney, City Allegation Final Disposition Discipline? Allegations Discipline Comments Improper Procedure Sustained Oral Reprim Oral Reprimand IA Number: 03-0419 STATUS: Completed Complainant: Pye, Gregory IA Number: 17-0709 STATUS: Completed Complainant: Thomas, Jacob IA Number: 22-0809 STATUS: Completed Complainant: Commander Sean Lohse-Johnson Printed: 10/5/2022 9:03:13 AM [by: Drake, Lisa (CI-StPaul) (Chiefs Office/Internal A] Page 1 of 1 | C5: ['https://assets.nationbuilder.com/cuapb/pages/270/attachments/original/1667360765/Hallstrom_-_Public_IA.pdf?1667360765'] | D5: ['Kurtis W. Hallstrom, badge #253400'] | E5: ['Department:St. Paul Police Department'] | F5: 750 | K5: =IF(Final_Cleaned_Data_V2!J5="Other", "Please specify here", "") | N5: =IF(Final_Cleaned_Data_V2!M5="Other", "Please specify here", "")
A6: 85 | B6: 5 EXHIBIT A UNITED STATES DISTRICT COURT DISTRICT OF MINNESOTA Dennis Melvin Hill, Plaintiff, vs. The City of Minneapolis, Officer Matthew Kaminski, Officer Jason Schmitt, and John Doe Officers, Defendants. COURT FILE NO. 13-cv-705 PJS/SER JOINT STIPULATION TO DISMISS THE CITY OF MINNEAPOLIS AND THE COMPLAINT WITH PREJUDICE The City of Minneapolis and Plaintiff, acting by and through their undersigned attorneys of record, hereby stipulate that, pursuant to Fed. R. Civ. P. 41, the Court shall dismiss Plaintiff's Complaint in its entirety, with prejudice, and without costs to any party. CASE 0:13-cv-00705-PJS-SER Doc. 34 Filed 09/02/14 Page 1 of 2 CASE 0:13-cv-00705-PJS-SER Doc. 34 Filed 09/02/14 Page 2 of 2 | C6: ['https://d3n8a8pro7vhmx.cloudfront.net/cuapb/pages/270/attachments/original/1626031083/kaminski_dismissal.pdf?1626031083'] | D6: ['Jason Schmitt, badge #6374', 'Matthew R. Kaminski, badge #3615'] | E6: ['Department:Minneapolis Police Department'] | F6: 777 | K6: =IF(Final_Cleaned_Data_V2!J6="Other", "Please specify here", "") | N6: =IF(Final_Cleaned_Data_V2!M6="Other", "Please specify here", "")
A7: 86 | B7: NOTICE OF REMOVAL, EXHIBIT B CASE 0:13-cv-00705-PJS-SER Doc. 1-2 Filed 03/27/13 Page 1 of 8 NOTICE OF REMOVAL, EXHIBIT B CASE 0:13-cv-00705-PJS-SER Doc. 1-2 Filed 03/27/13 Page 2 of 8 NOTICE OF REMOVAL, EXHIBIT B CASE 0:13-cv-00705-PJS-SER Doc. 1-2 Filed 03/27/13 Page 3 of 8 NOTICE OF REMOVAL, EXHIBIT B CASE 0:13-cv-00705-PJS-SER Doc. 1-2 Filed 03/27/13 Page 4 of 8 NOTICE OF REMOVAL, EXHIBIT B CASE 0:13-cv-00705-PJS-SER Doc. 1-2 Filed 03/27/13 Page 5 of 8 NOTICE OF REMOVAL, EXHIBIT B CASE 0:13-cv-00705-PJS-SER Doc. 1-2 Filed 03/27/13 Page 6 of 8 NOTICE OF REMOVAL, EXHIBIT B CASE 0:13-cv-00705-PJS-SER Doc. 1-2 Filed 03/27/13 Page 7 of 8 NOTICE OF REMOVAL, EXHIBIT B CASE 0:13-cv-00705-PJS-SER Doc. 1-2 Filed 03/27/13 Page 8 of 8 | C7: ['https://d3n8a8pro7vhmx.cloudfront.net/cuapb/pages/270/attachments/original/1626030759/kaminski_complaint_.pdf?1626030759'] | D7: ['Jason Schmitt, badge #6374', 'Matthew R. Kaminski, badge #3615'] | E7: ['Department:Minneapolis Police Department'] | F7: 783 | K7: =IF(Final_Cleaned_Data_V2!J7="Other", "Please specify here", "") | N7: =IF(Final_Cleaned_Data_V2!M7="Other", "Please specify here", "")
A8: 87 | B8: UNITED STATES DISTRICT COURT DISTRICT OF MINNESOTA Madelyn R. Milton, Plaintiff, vs. City of Minneapolis, Defendant. Civ. No.: 15-1930 (RHK/TNL) ORDER OF DISMISSAL OF CITY OF MINNEAPOLIS The above-captioned matter came before the Court on the parties' Stipulation of Dismissal of City of Minneapolis (Doc. No. 16). Based upon the parties' Stipulation, IT IS ORDERED that all claims against Defendant City of Minneapolis are DISMISSED WITH PREJUDICE, without costs or fees to any party. LET JUDGMENT BE ENTERED ACCORDINGLY. Dated: October 14, 2015 s/Richard H. Kyle RICHARD H. KYLE United States District Judge CASE 0:15-cv-01930-RHK-TNL Document 17 Filed 10/14/15 Page 1 of 1 | C8: ['https://d3n8a8pro7vhmx.cloudfront.net/cuapb/pages/270/attachments/original/1614450573/Milton_v._Barze_Document_17_Order_of_Dismissal_City_of_Mpls.pdf?1614450573'] | D8: ['Tyrone Barze, badge #330'] | E8: ['Department:Minneapolis Police Department'] | F8: 794 | K8: =IF(Final_Cleaned_Data_V2!J8="Other", "Please specify here", "") | N8: =IF(Final_Cleaned_Data_V2!M8="Other", "Please specify here", "")
A9: 88 | B9: 27-CV-05-007993 Filed in District Court State of Minnesota 8/27/2020 1:57 PM STATE OF MINNESOTA DISTRICT COURT COUNTY OF HENNEPIN FOURTH JUDICIAL DISTRICT Joshua Doring, Case File N0: 27-CV-05-007993 Plaintiff, vs. Ofcer Michael Kennedy, et a1, Defendants. SATISFACTION OF JUDGMENT FULL SATISFACTION: I, Jason M. Hiveley, the undersigned judgment creditor's attorney, hereby certify that the judgment entered and docketed in the above named court in the above entitled action on December 6, 2005, in favor of the City of Champlin, James Johans and Michael Kennedy and against Joshua Doring in the amount of $2,822.46 is fully satisfied and the Court Administrator shall record the same. (Signatye/ofJidgir'zem Credito "" Attorney) Sworn and subscribed to before me this 2nd day of March, 2012. - - REBECCA J. EITREIM Notary Public | C9: ['https://assets.nationbuilder.com/cuapb/pages/270/attachments/original/1671380372/kennedy_judgement_27-CV-05-007993.pdf?1671380372'] | D9: ['Michael Kennedy, badge #3693'] | E9: ['Department:Minneapolis Police Department'] | F9: 830 | K9: =IF(Final_Cleaned_Data_V2!J9="Other", "Please specify here", "") | N9: =IF(Final_Cleaned_Data_V2!M9="Other", "Please specify here", "")
A10: 89 | B10: Ex-officer charged with theft from Scouts POST BULLETIN October 23, 2000 04:00 AM STILLWATER, Minn. -- Former Police Sgt. Davin Miller has been charged with theft for allegedly taking money from a scouting troop he led. The Washington County Attorney's office on Friday charged Miller, 41, of Hudson, Wis., of misappropriating more than $2,000 from Stillwater Police Explorer POST 521, which he supervised from 1992 until February 2000, when he resigned from the department. The charge carries a maximum penalty of five years in jail and a $10,000 fine. According to a report by the state auditor's office that was forwarded to the county attorney, the actual amount misappropriated could be more than $10,700. Miller was the lone signatory on the Explorer POST bank account for more than five years, during which the transactions singled out by the auditors occurred. | C10: ['https://assets.nationbuilder.com/cuapb/pages/1472/attachments/original/1670343760/Miller_Davin_Ex-officer_charged_with_theft_from_Scouts.pdf?1670343760'] | D10: ['Davin Miller, badge #None'] | E10: ['Department:Stillwater Police Department'] | F10: 880 | K10: =IF(Final_Cleaned_Data_V2!J10="Other", "Please specify here", "") | N10: =IF(Final_Cleaned_Data_V2!M10="Other", "Please specify here", "")
A11: 90 | B11: HOME MN NEWS Belle Plaine o cer suspected of DWI a er driving 96 mph BMTN STAFF • UPDATED: MAR 8, 2018 · ORIGINAL: NOV 21, 2012 State patrol of cial a Belle Plaine police of cer Bran Michael Paek wa topped b a tate trooper on Highwa 169 roughl 40 mile outhwet of the Twin Citie near Belle Plaine, at 2:26 a.m. Tueda after driving 96 mph zone, the Belle Plaine Herald report. He wa off-dut at the time, WCCO report. The 32-ear-old of cer wa given a breath tet that howed a .17 blood-alcohol content level, twice the legal limit, the newpaper report. He had a imilar violation in 2003, the newpaper a. No one with the Belle Plaine police commented for a tor on Fox 9: KMSP-TV Belle Plaine officer suspected of DWI after driving 96 mph - Bring Me ... https://bringmethenews.com/minnesota-news/belle-plaine-officer-suspe... 1 of 1 12/27/2022, 12:54 AM | C11: ['https://assets.nationbuilder.com/cuapb/pages/1472/attachments/original/1672124550/Pasek_3_Belle_Plaine_officer_suspected_of_DWI_after_driving_96_mph_-_Bring_Me_The_News.pdf?1672124550'] | D11: ['Bryan M. Pasek, badge #None'] | E11: ['Department:Belle Plaine Police Department'] | F11: 881 | K11: =IF(Final_Cleaned_Data_V2!J11="Other", "Please specify here", "") | N11: =IF(Final_Cleaned_Data_V2!M11="Other", "Please specify here", "")
A12: 91 | B12: UNITED STATES DISTRICT COURT District of Minnesota Madelyn R. Milton, JUDGMENT IN A CIVIL CASE Plaintiff, v. Case Number: 15-1930 (RHK/TNL) City of Minneapolis, Defendant(s). Jury Verdict. This action came before the Court for a trial by jury. The issues have been tried and the jury has rendered its verdict. X Decision by Court. This action came to trial or hearing before the Court. The issues have been tried or heard and a decision has been rendered. IT IS ORDERED AND ADJUDGED THAT: All claims against Defendant City of Minneapolis are DISMISSED WITH PREJUDICE, without costs or fees to any party. Date: 10/13/2015 RICHARD D. SLETTEN, CLERK s/M. Price (By) M. Price, Deputy Clerk CASE 0:15-cv-01930-RHK-TNL Document 18 Filed 10/14/15 Page 1 of 1 | C12: ['https://d3n8a8pro7vhmx.cloudfront.net/cuapb/pages/270/attachments/original/1614450707/Milton_v._Barze_Document_18_Judgment.pdf?1614450707'] | D12: ['Tyrone Barze, badge #330'] | E12: ['Department:Minneapolis Police Department'] | F12: 881 | K12: =IF(Final_Cleaned_Data_V2!J12="Other", "Please specify here", "") | N12: =IF(Final_Cleaned_Data_V2!M12="Other", "Please specify here", "")
A13: 92 | B13: UNITED STATES DISTRICT COURT District of Minnesota Jon Gauthier, JUDGMENT IN A CIVIL CASE Plaintiff, v. Case Number: 15-cv-3068 (RHK/KMM) City of Minneapolis and Jordan Davis, Defendant(s). Jury Verdict. This action came before the Court for a trial by jury. The issues have been tried and the jury has rendered its verdict. X Decision by Court. This action came to trial or hearing before the Court. The issues have been tried or heard and a decision has been rendered. IT IS ORDERED AND ADJUDGED THAT: all claims against Defendant City of Minneapolis are DISMISSED WITH PREJUDICE and without costs or fees to any party Date: 12/28/2016 RICHARD D. SLETTEN, CLERK s/K. Krulas (By) K. Krulas, Deputy Clerk CASE 0:15-cv-03068-RHK-KMM Document 34 Filed 12/29/16 Page 1 of 1 | C13: ['https://d3n8a8pro7vhmx.cloudfront.net/cuapb/pages/270/attachments/original/1614974721/2016JonGauthierJudgment.pdf?1614974721'] | D13: ['Jordan Davis, badge #1434'] | E13: ['Department:Minneapolis Police Department'] | F13: 890 | K13: =IF(Final_Cleaned_Data_V2!J13="Other", "Please specify here", "") | N13: =IF(Final_Cleaned_Data_V2!M13="Other", "Please specify here", "")
A14: 93 | B14: Minneapolis Police Department Discipline Worksheet Sgt. Shannon Barnette, #0268 Employee's Name and ID Number 5/25/2017 Date of Incident Discipline Panel Recommendation OPCR 17-10527 Administrative Case Number Policy Number Policy Description Category Disposition 5-105 (A)(4) Professional Code of Conduct Merit 4-602 Report Writing Merit Deputy Chief of Professional Standards Date 13.43 - Personnel Data 1' 14' sc;c:' " 1332747 Minneapolis Police Department Discipline Worksheet Office of the Chief of Police Policy Number Policy Description Category Disposition 5-105 (A)(4) Professional Code of Conduct B Merit 4-602 Report Writing B Merit Final Disposition 5-105 (A)(4) Professional Code of Conduct, Sustained - B 4-602 Report Writing, Sustained - B Letter of Reprimand Chief of Police MP-1408 (Revised 12/15) 2 Date 1332748 1332749 1332750 | C14: ['https://assets.nationbuilder.com/cuapb/pages/1509/attachments/original/1753851699/17-10527_Shannon_Barnette-Discipline_Memo.pdf?1753851699'] | D14: ['Shannon L. Barnette, badge #268'] | E14: ['Department:Minneapolis Police Department'] | F14: 893 | K14: =IF(Final_Cleaned_Data_V2!J14="Other", "Please specify here", "") | N14: =IF(Final_Cleaned_Data_V2!M14="Other", "Please specify here", "")
A15: 94 | B15: Skip to content Offender Information Demographic Information** MNDOC Offender ID: 243907 Name: Aaron Joseph Heuer Birth Date: 10/11/1983 Current Status: Incarcerated as of 05/08/2014. Currently at a non-DOC facility. Sentence Date: 05/08/2014 Anticipated Release Date: 07/23/2035 Expiration Date: Life Caseworker: Abby Domagalski 651-779-2754 Current Offense Information Highest Ranked Offense: Criminal Sexual Conduct Court File Number(s): Otter Tail - 56-CR-13-2467 Otter Tail - 56-CR-13-1927 Mille Lacs - 48-CR-14-524 Other Links Go to MN Courts website (https://pa.courts.state.mn.us/default.aspx) to look up court case information (opens in a new window). Go to BCA website (https://chs.state.mn.us/) to look up criminal history information (opens in a new window). Offender Locator Details https://coms.doc.state.mn.us/publicviewer/OffenderDetails/Index/2439... 1 of 2 11/24/2022, 12:49 PM | C15: ['https://assets.nationbuilder.com/cuapb/pages/1472/attachments/original/1669315796/Aaron_Heuer_MN_DOC_Details.pdf?1669315796'] | D15: ['Aaron Heuer, badge #None'] | E15: ['Department:Mille Lacs County Sheriffs Office'] | F15: 895 | K15: =IF(Final_Cleaned_Data_V2!J15="Other", "Please specify here", "") | N15: =IF(Final_Cleaned_Data_V2!M15="Other", "Please specify here", "")
A16: 95 | B16: Skip to content Offender Information Demographic Information** MNDOC Offender ID: 237622 Name: William Allan Jacobs Birth Date: 07/11/1943 Current Status: Incarcerated as of 04/11/2012. Currently at MCF Lino Lakes (https://mn.gov /doc/facilities/lino-lakes/). Sentence Date: 04/09/2012 Anticipated Release Date: 03/04/2024 Expiration Date: Life Caseworker: Ryan Schill 651-717-6100 Current Offense Information Highest Ranked Offense: Criminal Sexual Conduct Court File Number(s): Hennepin - 27CR103626 Hennepin - 27CR103386 Other Links Go to MN Courts website (https://pa.courts.state.mn.us/default.aspx) to look up court case information (opens in a new window). Go to BCA website (https://chs.state.mn.us/) to look up criminal history information (opens in a new window). Offender Locator Details https://coms.doc.state.mn.us/publicviewer/OffenderDetails/Index/2376... 1 of 2 11/24/2022, 10:26 PM | C16: ['https://assets.nationbuilder.com/cuapb/pages/1472/attachments/original/1669350422/William_Jacobs_MN_DOC_Record.pdf?1669350422'] | D16: ['William Jacobs, badge #None'] | E16: ['Department:Minneapolis Park Police Department'] | F16: 898 | K16: =IF(Final_Cleaned_Data_V2!J16="Other", "Please specify here", "") | N16: =IF(Final_Cleaned_Data_V2!M16="Other", "Please specify here", "")
... A104: 183 | B104: Home >Legislative File 2021-00539 >RCA Legal Se lement: Workers' Compensa on claim of Andrew Hegseth (RCA-2021-00525) ORIGINATING DEPARTMENT Finance & Property Services To Commi ee(s) # Commi ee Name Mee ng Date 1 Policy & Government Oversight Commi ee May 12, 2021 LEAD STAFF: Emily Ann Colby PRESENTED BY: Emily Ann Colby Ac on Item(s) # File Type Subcategory Item Descrip on 1 Ac on Se lement Approving the Workers' Compensa on claim of Andrew Hegseth by payment of $90,000 to Mr. Hegseth and his a orneys Mesuer Law Firm and authorizing the City A orney's Office to execute any documents necessary to effectuate the se lement. Ward / Neighborhood / Address RCA-2021-00525 - Legal Settlement: Workers' Compensation claim of ... https://lims.minneapolismn.gov/RCA/7937 1 of 2 12/4/2021, 12:36 AM # Ward Neighborhood Address 1. Not Applicable Background Analysis Fomer MPD officer sustained work-related injuries. The par es reached a tenta ve se lement by payment of $90,000 from fund 06930-1450100-789401-145400. Risk Managment believes the se lement is in the best interests of the City and recommends approval by the Commi ee and the City Council. FISCAL NOTE • Legal Se lement: Workers' Compensa on claim of Andrew Hegseth - Fiscal Note RCA-2021-00525 - Legal Settlement: Workers' Compensation claim of ... https://lims.minneapolismn.gov/RCA/7937 2 of 2 12/4/2021, 12:36 AM | C104: ["https://d3n8a8pro7vhmx.cloudfront.net/cuapb/pages/1462/attachments/original/1638637588/RCA-2021-00525_-_Legal_Settlement_Workers'_Compensation_claim_of_Andrew_Hegseth.pdf?1638637588"] | D104: ['Andrew Hegseth, badge #2878'] | E104: ['Department:Minneapolis Police Department'] | F104: 1380 | K104: =IF(Final_Cleaned_Data_V2!J104="Other", "Please specify here", "") | N104: =IF(Final_Cleaned_Data_V2!M104="Other", "Please specify here", "")
A105: 184 | B105: Too_Long:Over 20 PagesCASE 0:15-cr-00247-PJS-SER Doc. 1 Filed 09/10/15 Page 1 of 23 CASE 0:15-cr-00247-PJS-SER Doc. 1 Filed 09/10/15 Page 2 of 23 CASE 0:15-cr-00247-PJS-SER Doc. 1 Filed 09/10/15 Page 3 of 23 CASE 0:15-cr-00247-PJS-SER Doc. 1 Filed 09/10/15 Page 4 of 23 CASE 0:15-cr-00247-PJS-SER Doc. 1 Filed 09/10/15 Page 5 of 23 CASE 0:15-cr-00247-PJS-SER Doc. 1 Filed 09/10/15 Page 6 of 23 CASE 0:15-cr-00247-PJS-SER Doc. 1 Filed 09/10/15 Page 7 of 23 CASE 0:15-cr-00247-PJS-SER Doc. 1 Filed 09/10/15 Page 8 of 23 CASE 0:15-cr-00247-PJS-SER Doc. 1 Filed 09/10/15 Page 9 of 23 CASE 0:15-cr-00247-PJS-SER Doc. 1 Filed 09/10/15 Page 10 of 23 CASE 0:15-cr-00247-PJS-SER Doc. 1 Filed 09/10/15 Page 11 of 23 CASE 0:15-cr-00247-PJS-SER Doc. 1 Filed 09/10/15 Page 12 of 23 CASE 0:15-cr-00247-PJS-SER Doc. 1 Filed 09/10/15 Page 13 of 23 CASE 0:15-cr-00247-PJS-SER Doc. 1 Filed 09/10/15 Page 14 of 23 CASE 0:15-cr-00247-PJS-SER Doc. 1 Filed 09/10/15 Page 15 of 23 CASE 0:15-cr-00247-PJS-SER Doc. 1 Filed 09/10/15 Page 16 of 23 CASE 0:15-cr-00247-PJS-SER Doc. 1 Filed 09/10/15 Page 17 of 23 CASE 0:15-cr-00247-PJS-SER Doc. 1 Filed 09/10/15 Page 18 of 23 CASE 0:15-cr-00247-PJS-SER Doc. 1 Filed 09/10/15 Page 19 of 23 CASE 0:15-cr-00247-PJS-SER Doc. 1 Filed 09/10/15 Page 20 of 23 | C105: ['https://assets.nationbuilder.com/cuapb/pages/1472/attachments/original/1669157534/Indictment_of_Jordan_Davis_15-CR-00247.pdf?1669157534'] | D105: ['Jordan Davis, badge #1434'] | E105: ['Department:Minneapolis Police Department'] | F105: 1392 | G105: TRUE | K105: =IF(Final_Cleaned_Data_V2!J105="Other", "Please specify here", "") | N105: =IF(Final_Cleaned_Data_V2!M105="Other", "Please specify here", "")
A106: 185 | B106: Fa  Election Results Weather Sports A Minnesota man was sentenced to 36 months in prison Friday for sexually assaulting and stalking a teenager while working as a police o Joshua Demmerly, 30, was charged in with sexually assault and stalking a teenager as an officer with the Warroad Police Department in A According to court documents, the victim claimed Demmerly told them that they were under investigation and the only way to get out of warrant was to spend time with him. Demmerly also allegedly gave the victim and other teens alcohol and tracked the victim's location via phone. The crimes were reported to take place when the victim was 16 and 17 years old. Demmerly pleaded guilty to two counts of criminal sexual conduct and two counts of stalking in September, according to court documen entering an Alford plea, a guilty plea in which the defendant still asserts innocence. He was sentenced on these counts Friday. He will serve a total of 36 months in the Minnesota Department of Corrections - St. Cloud. He for 221 days served. Most Read Ex-officer sentenced for sexually assaulting, stalking teenager (KVLY) Published: Nov. 9, 2019 at 3:17 PM CST  UPDATE: 2 dead in Lisbon structure fire Ex-officer sentenced for sexually assaulting, stalking teenager https://www.valleynewslive.com/content/news/Ex-officer-sentenced-for-sexually-assaulting-stalking... 1 of 3 11/22/2022, 5:06 PM | C106: ['https://assets.nationbuilder.com/cuapb/pages/1472/attachments/original/1669158590/Ex-officer_sentenced_for_sexually_assaulting__stalking_teenager.pdf?1669158590'] | D106: ['Joshua Demmerly, badge #None'] | E106: ['Department:Warroad Police Department'] | F106: 1398 | K106: =IF(Final_Cleaned_Data_V2!J106="Other", "Please specify here", "") | N106: =IF(Final_Cleaned_Data_V2!M106="Other", "Please specify here", "")
A107: 186 | B107: City of Minneapolis Request for Committee Action To: Ways & Means Date: 9/8/2015 From: City Attorney's Office Prepared by: Kristin Sarff Presented by: Susan Segal File type: Action Subcategory: Settlement Subject: Settlement of a lawsuit by Louis Tate. Description: Approving the settlement of the lawsuit of Louis Tate by payment of $25,000.00 to Louis Tate and his attorneys from Fund/Org. 06900 1500100 145400, and authorize the City Attorney's Office to execute any documents necessary to effectuate settlement. Previous Actions: None Ward/Neighborhood/Address: Ward 9 Midtown Phillips Intersection of 14th Avenue South and 24th Street East Background/Analysis: Plaintiff alleges causes of action for excessive force, assault, and battery. The parties have negotiated a proposed settlement in the amount of $25,000.00, including all claims for damages, attorneys' fees and costs. The City Attorney's Office and MPD administration believe that the proposed settlement is in the best interests of the City and recommend approval by this Committee and the City Council. Financial Review: No additional appropriation required, amount included in current budget. ☐ Future budget impact anticipated. ☐ Approved by the Permanent Review Committee. ☐ Meets Small and Underutilized Business Program goals. Attachments: 1. None | C107: ['https://d3n8a8pro7vhmx.cloudfront.net/cuapb/pages/270/attachments/original/1615063804/2015LouisTate.pdf?1615063804'] | D107: ['Brian Anderson, badge #91', 'Steven Lecy, badge #4057', 'Tracy Gross, badge #4070'] | E107: ['Department:Minneapolis Police Department'] | F107: 1404 | K107: =IF(Final_Cleaned_Data_V2!J107="Other", "Please specify here", "") | N107: =IF(Final_Cleaned_Data_V2!M107="Other", "Please specify here", "")
A108: 187 | B108: Home >Legislative File 2021-00659 >RCA Legal Se lement: Workers' Compensa on claims of Jeffrey Kading (RCA-2021-00673) ORIGINATING DEPARTMENT Finance & Property Services To Commi ee(s) # Commi ee Name Mee ng Date 1 Policy & Government Oversight Commi ee Jun 16, 2021 LEAD STAFF: Emily Ann Colby PRESENTED BY: Emily Ann Colby Ac on Item(s) # File Type Subcategory Item Descrip on 1 Ac on Se lement Approving the Workers' Compensa on claims of Jeffrey Kading by payment of $125,000 to Jeffrey Kading and his a orney(s), Meuser Law Firm, and authorizing the City A orney's Office to execute any documents necessary to effectuate the se lement. Ward / Neighborhood / Address RCA-2021-00673 - Legal Settlement: Workers' Compensation claims of ... https://lims.minneapolismn.gov/RCA/8119 1 of 2 12/4/2021, 12:41 AM # Ward Neighborhood Address 1. Not Applicable Background Analysis Former Minneapolis employee sustained work-related injuries. The par es reached a tenta ve se lement by payment of $125,000 from fund 06930-1450100-789401-145400. Risk Management believes this se lement is in the best interests of the City and recommends approval by the Commi ee and the City Council. FISCAL NOTE • Legal Se lement: Workers' Compensa on claims of Jeffrey Kading - Fiscal Note RCA-2021-00673 - Legal Settlement: Workers' Compensation claims of ... https://lims.minneapolismn.gov/RCA/8119 2 of 2 12/4/2021, 12:41 AM | C108: ["https://d3n8a8pro7vhmx.cloudfront.net/cuapb/pages/1462/attachments/original/1638637590/RCA-2021-00673_-_Legal_Settlement_Workers'_Compensation_claims_of_Jeffrey_Kading.pdf?1638637590"] | D108: ['Jeff Kading, badge #3598'] | E108: ['Department:Minneapolis Police Department'] | F108: 1406 | K108: =IF(Final_Cleaned_Data_V2!J108="Other", "Please specify here", "") | N108: =IF(Final_Cleaned_Data_V2!M108="Other", "Please specify here", "")
A109: 188 | B109: Home >Legislative File 2021-00403 >RCA Legal Se lement: Workers' Compensa on claim of Tammy Werner (RCA-2021-00431) ORIGINATING DEPARTMENT Finance & Property Services To Commi ee(s) # Commi ee Name Mee ng Date 1 Policy & Government Oversight Commi ee Apr 14, 2021 LEAD STAFF: Emily Ann Colby PRESENTED BY: Emily Ann Colby Ac on Item(s) # File Type Subcategory Item Descrip on 1 Ac on Se lement Approving the Workers' Compensa on claim of Tammy Werner by payment of $95,000 to Ms. Werner and her a orneys Meuser Law Firm, and authorizing the City A orney's Office to execute any documents necessary to effectuate the se lement. Ward / Neighborhood / Address RCA-2021-00431 - Legal Settlement: Workers' Compensation claim of ... https://lims.minneapolismn.gov/RCA/7805 1 of 2 12/4/2021, 12:28 AM # Ward Neighborhood Address 1. Not Applicable Background Analysis Former police officer Tammy Werner sustained admi ed work-related injuries. The par es have reached a tenta ve se lement by payment of $95,000 from Fund 06930-1450100-789410-145400. Risk Management believes the se lement is in the best interests of the City and recommends approval by this Commi ee and the City Council. FISCAL NOTE • Legal Se lement: Workers' Compensa on claim of Tammy Werner - Fiscal Note RCA-2021-00431 - Legal Settlement: Workers' Compensation claim of ... https://lims.minneapolismn.gov/RCA/7805 2 of 2 12/4/2021, 12:28 AM | C109: ["https://d3n8a8pro7vhmx.cloudfront.net/cuapb/pages/1462/attachments/original/1638637585/RCA-2021-00431_-_Legal_Settlement_Workers'_Compensation_claim_of_Tammy_Werner.pdf?1638637585"] | D109: ['Tammy Werner, badge #2119'] | E109: ['Department:Minneapolis Police Department'] | F109: 1406 | K109: =IF(Final_Cleaned_Data_V2!J109="Other", "Please specify here", "") | N109: =IF(Final_Cleaned_Data_V2!M109="Other", "Please specify here", "")
A110: 189 | B110: Home >Legislative File 2021-00542 >RCA Legal Se lement: Workers' Compensa on claim of Gene Suker (RCA-2021-00545) ORIGINATING DEPARTMENT Finance & Property Services To Commi ee(s) # Commi ee Name Mee ng Date 1 Policy & Government Oversight Commi ee May 12, 2021 LEAD STAFF: Emily Ann Colby PRESENTED BY: Emily Ann Colby Ac on Item(s) # File Type Subcategory Item Descrip on 1 Ac on Se lement Approving the Workers' Compensa on claim of Gene Suker by payment of $200,000 over three years to Mr. Gene Suker and his a orney's Meuser Law Firm and authorizing the City A orney's Office to execute any documents necessary to effectuate the se lement. Ward / Neighborhood / Address RCA-2021-00545 - Legal Settlement: Workers' Compensation claim of ... https://lims.minneapolismn.gov/RCA/7955 1 of 2 12/4/2021, 12:31 AM # Ward Neighborhood Address 1. Not Applicable Background Analysis Former employee sustained work-related injuries. The par es reached a tenta ve se lement by payment of $200,000 over three years from fund 06930-1450100-789401-145400. Risk Management believes the se lement is in the best interrsts of the City and recommends approval by the Commi ee and the City Council. FISCAL NOTE • Legal Se lement: Workers' Compensa on claim of Gene Suker - Fiscal Note RCA-2021-00545 - Legal Settlement: Workers' Compensation claim of ... https://lims.minneapolismn.gov/RCA/7955 2 of 2 12/4/2021, 12:31 AM | C110: ["https://d3n8a8pro7vhmx.cloudfront.net/cuapb/pages/1462/attachments/original/1638637589/RCA-2021-00545_-_Legal_Settlement_Workers'_Compensation_claim_of_Gene_Suker.pdf?1638637589"] | D110: ['Gene Suker, badge #7004'] | E110: ['Department:Minneapolis Police Department'] | F110: 1407 | K110: =IF(Final_Cleaned_Data_V2!J110="Other", "Please specify here", "") | N110: =IF(Final_Cleaned_Data_V2!M110="Other", "Please specify here", "")
A111: 190 | B111: Home >Legislative File 2021-00544 >RCA Legal Se lement: Workers' Compensa on claim of David Robins (RCA-2021-00547) ORIGINATING DEPARTMENT Finance & Property Services To Commi ee(s) # Commi ee Name Mee ng Date 1 Policy & Government Oversight Commi ee May 12, 2021 LEAD STAFF: Emily Ann Colby PRESENTED BY: Emily Ann Colby Ac on Item(s) # File Type Subcategory Item Descrip on 1 Ac on Se lement Approving the Workers' Compensa on claim of David Robins by payment of $125,000 over two years to Mr. Robins and his a orneys Meuser Law Firm and authorizing the City A orney's Office to execute any documents necessary to effectuate the se lement. Ward / Neighborhood / Address RCA-2021-00547 - Legal Settlement: Workers' Compensation claim of ... https://lims.minneapolismn.gov/RCA/7957 1 of 2 12/4/2021, 12:35 AM # Ward Neighborhood Address 1. Not Applicable Background Analysis Former employee sustained work-related injuries. The par es reached a tenta ve se lement by payment of $125,000 over two years from fund 06930-1450100-789401-145400. Risk Management believes this se lement to be in the best interests of the City and recommends approval by the Commi ee and the City Council. FISCAL NOTE • Legal Se lement: Workers' Compensa on claim of David Robins - Fiscal Note RCA-2021-00547 - Legal Settlement: Workers' Compensation claim of ... https://lims.minneapolismn.gov/RCA/7957 2 of 2 12/4/2021, 12:35 AM | C111: ["https://d3n8a8pro7vhmx.cloudfront.net/cuapb/pages/1462/attachments/original/1638637590/RCA-2021-00547_-_Legal_Settlement_Workers'_Compensation_claim_of_David_Robins.pdf?1638637590"] | D111: ['David Robins, badge #6046'] | E111: ['Department:Minneapolis Police Department'] | F111: 1408 | K111: =IF(Final_Cleaned_Data_V2!J111="Other", "Please specify here", "") | N111: =IF(Final_Cleaned_Data_V2!M111="Other", "Please specify here", "")
A112: 191 | B112: Home >Legislative File 2021-01037 >RCA Legal se lement: Workers' Compensa on claim of James Burns (RCA-2021-01068) ORIGINATING DEPARTMENT Finance & Property Services To Commi ee(s) # Commi ee Name Mee ng Date 1 Policy & Government Oversight Commi ee Sep 22, 2021 LEAD STAFF: Emily Ann Colby PRESENTED BY: Emily Ann Colby Ac on Item(s) # File Type Subcategory Item Descrip on 1 Ac on Se lement Approving the se lement of the Workers' Compensa on claim of James Burns, by payment of $125,000 to James Burns and a orney, Meuser Law Firm, and authorizing the City A orney's Office to execute any documents necessary to effectuate the se lement. Previous Ac ons None RCA-2021-01068 - Legal settlement: Workers' Compensation claim of ... https://lims.minneapolismn.gov/RCA/8597 1 of 2 12/4/2021, 1:15 AM Ward / Neighborhood / Address # Ward Neighborhood Address 1. Not Applicable Background Analysis City employee sustained work-related injuries. The par es have reached a tenta ve se lement by payment of $125,000 from fund 06930-1450100-789401-145400. Risk Management believes the se lement is in the best interests of the City and recommends approval by the Commi ee and the City Council. FISCAL NOTE • Legal se lement: Workers' Compensa on claim of James Burns - Fiscal Note RCA-2021-01068 - Legal settlement: Workers' Compensation claim of ... https://lims.minneapolismn.gov/RCA/8597 2 of 2 12/4/2021, 1:15 AM | C112: ["https://d3n8a8pro7vhmx.cloudfront.net/cuapb/pages/1462/attachments/original/1638637598/RCA-2021-01068_-_Legal_settlement_Workers'_Compensation_claim_of_James_Burns.pdf?1638637598"] | D112: ['James L. Burns, badge #884'] | E112: ['Department:Minneapolis Police Department'] | F112: 1408 | K112: =IF(Final_Cleaned_Data_V2!J112="Other", "Please specify here", "") | N112: =IF(Final_Cleaned_Data_V2!M112="Other", "Please specify here", "")
A113: 192 | B113: STAR TRIBUNE › Annotations Off-duty McLeod County deputy, Norwood Young America man from April ್೓ shooting identified APRIL ೅ೇ, ೅ೃೄೈ The Department of Public Safety released the names Friday of an off-duty deputy sheriff and another man involved in the April  shooting at a Kwik Trip store in Norwood Young America. McLeod County Sheriff's Deputy Matthew Allen Wyatt, , stopped to refuel at the gas station at  Reform St. when a call about an unruly patron came in around : a.m. Wyatt struggled with the patron, Michael Thomas Montgomery, , of Norwood Young America, before a firearm discharged, according to Carver County Sheriff Jim Olson. Montgomery fled the scene before being apprehended a few blocks away. Both men were treated for noncritical injuries. It is still unclear who fired the weapon and whether either man will face criminal charges related to the incident. The Bureau of Criminal Apprehension is investigating Wyatt's use of force and will present its findings to the Carver County attorney's office for review, according to a news release. Annotations · Report a problem COPY https://outline.com/dw3edy ✕ HOME · TERMS · PRIVACY · DMCA · CONTACT Outline is a free service for reading and annotating news articles. We remove the clutter so you can analyze and comment on the content. In today's climate of widespread misinformation, Outline empowers readers to verify the facts. | C113: ['https://d3n8a8pro7vhmx.cloudfront.net/cuapb/pages/270/attachments/original/1627047812/Off-duty_McLeod_County_deputy__Norwood_Young_America_man_from_April_17_shooting_identified.pdf?1627047812'] | D113: ['Matthew A. Wyatt, badge #None', 'Michael Zeug, badge #None'] | E113: ['Department:', 'Department:McLeod County Sheriffs Office'] | F113: 1409 | K113: =IF(Final_Cleaned_Data_V2!J113="Other", "Please specify here", "") | N113: =IF(Final_Cleaned_Data_V2!M113="Other", "Please specify here", "")
A114: 193 | B114: Home >Legislative File 2021-00536 >RCA Legal Se lement: Workers' Compensa on claims of Luke Eckert (RCA-2021-00524) ORIGINATING DEPARTMENT Finance & Property Services To Commi ee(s) # Commi ee Name Mee ng Date 1 Policy & Government Oversight Commi ee May 12, 2021 LEAD STAFF: Emily Ann Colby PRESENTED BY: Emily Ann Colby Ac on Item(s) # File Type Subcategory Item Descrip on 1 Ac on Se lement Approving the Workers' Compensa on claims of Luke Eckert by payment of $175,000 over three years to Mr. Eckert and his a orneys Meuser Law Firm and authorizing the City A orney's Office to execute any documents necessary to effectuate the se lement. Ward / Neighborhood / Address RCA-2021-00524 - Legal Settlement: Workers' Compensation claims of... https://lims.minneapolismn.gov/RCA/7936 1 of 2 12/4/2021, 12:34 AM # Ward Neighborhood Address 1. Not Applicable Background Analysis Former MPD Officer sustained work-related injuries. The par es reached a tenta ve se lement by payment of $175,000 over three years from fund 06930-1450100-789401-145400. Risk Management believes the se lement is in the best interests of hte City and recommends approval by the Commi ee and the City Council. FISCAL NOTE • Legal Se lement: Workers' Compensa on claims of Luke Eckert - Fiscal Note RCA-2021-00524 - Legal Settlement: Workers' Compensation claims of... https://lims.minneapolismn.gov/RCA/7936 2 of 2 12/4/2021, 12:34 AM | C114: ["https://d3n8a8pro7vhmx.cloudfront.net/cuapb/pages/1462/attachments/original/1638637587/RCA-2021-00524_-_Legal_Settlement_Workers'_Compensation_claims_of_Luke_Eckert.pdf?1638637587"] | D114: ['Luke Eckert, badge #1715'] | E114: ['Department:Minneapolis Police Department'] | F114: 1411 | K114: =IF(Final_Cleaned_Data_V2!J114="Other", "Please specify here", "") | N114: =IF(Final_Cleaned_Data_V2!M114="Other", "Please specify here", "")
A115: 194 | B115: Home >Legislative File 2021-00661 >RCA Legal Se lement: Workers' Compensa on claim of Tracy Gross (RCA-2021-00682) ORIGINATING DEPARTMENT Finance & Property Services To Commi ee(s) # Commi ee Name Mee ng Date 1 Policy & Government Oversight Commi ee Jun 16, 2021 LEAD STAFF: Emily Ann Colby PRESENTED BY: Emily Ann Colby Ac on Item(s) # File Type Subcategory Item Descrip on 1 Ac on Se lement Approving the Workers' Compensa on claim of Tracy Gross by payment of $150,000 over three years to Ms. Gross and her a orney, Meuser Law Firm, and authorizing the City A orney's Office to execute any documents necessary to effectuate the se lement. Ward / Neighborhood / Address RCA-2021-00682 - Legal Settlement: Workers' Compensation claim of T... https://lims.minneapolismn.gov/RCA/7987 1 of 2 12/4/2021, 12:41 AM # Ward Neighborhood Address 1. Not Applicable Background Analysis Former Minneaplis employee sustained work-related injuries. The par es reached a tenta ve se lment by payment of $150,000 over 3 years from fund 06930-1450100-789401-145-400. Risk Management believes the se lement is in the best interests of the City and recommends aproval by the Commi ee and the City Counsel. FISCAL NOTE • Legal Se lement: Workers' Compensa on claim of Tracy Gross - Fiscal Note RCA-2021-00682 - Legal Settlement: Workers' Compensation claim of T... https://lims.minneapolismn.gov/RCA/7987 2 of 2 12/4/2021, 12:41 AM | C115: ["https://d3n8a8pro7vhmx.cloudfront.net/cuapb/pages/1462/attachments/original/1638637592/RCA-2021-00682_-_Legal_Settlement_Workers'_Compensation_claim_of_Tracy_Gross.pdf?1638637592"] | D115: ['Tracy Gross, badge #4070'] | E115: ['Department:Minneapolis Police Department'] | F115: 1413 | K115: =IF(Final_Cleaned_Data_V2!J115="Other", "Please specify here", "") | N115: =IF(Final_Cleaned_Data_V2!M115="Other", "Please specify here", "")
A116: 195 | B116: Home >Legislative File 2021-00860 >RCA Legal Se lement: Workers' Compensa on claim of Christopher Steward (RCA-2021-00892) ORIGINATING DEPARTMENT Finance & Property Services To Commi ee(s) # Commi ee Name Mee ng Date 1 Policy & Government Oversight Commi ee Aug 4, 2021 LEAD STAFF: Emily Ann Colby PRESENTED BY: Emily Ann Colby Ac on Item(s) # File Type Subcategory Item Descrip on 1 Ac on Se lement Approving the Workers' Compensa on claims of Christopher Steward by payment of $130,000 to Christopher Steward and his a orney Meuser Law Firm, and authorizing the City A orney's Office to execute any documents necessary to effectuate the se lement. Ward / Neighborhood / Address RCA-2021-00892 - Legal Settlement: Workers' Compensation claim of C... https://lims.minneapolismn.gov/RCA/8385 1 of 2 12/4/2021, 12:51 AM # Ward Neighborhood Address 1. All Wards Background Analysis City of Minneapolis employee sustained work-related injuries. The par es reached a tenta ve se lement by payment of $130,000 from fund 06930-1450100-789401-145400. Risk Management believes the se lement is in the best interests of the City and recommends approval by the Comi ee and the City Council. FISCAL NOTE • Legal Se lement: Workers' Compensa on claim of Christopher Steward - Fiscal Note RCA-2021-00892 - Legal Settlement: Workers' Compensation claim of C... https://lims.minneapolismn.gov/RCA/8385 2 of 2 12/4/2021, 12:51 AM | C116: ["https://d3n8a8pro7vhmx.cloudfront.net/cuapb/pages/1462/attachments/original/1638637593/RCA-2021-00892_-_Legal_Settlement_Workers'_Compensation_claim_of_Christopher_Steward.pdf?1638637593"] | D116: ['Christopher Steward, badge #6823'] | E116: ['Department:Minneapolis Police Department'] | F116: 1413 | K116: =IF(Final_Cleaned_Data_V2!J116="Other", "Please specify here", "") | N116: =IF(Final_Cleaned_Data_V2!M116="Other", "Please specify here", "")
A117: 196 | B117: Home >Legislative File 2021-00859 >RCA Legal Se lement: Workers' Compensa on claim of Mark Sauer (RCA-2021-00896) ORIGINATING DEPARTMENT Finance & Property Services To Commi ee(s) # Commi ee Name Mee ng Date 1 Policy & Government Oversight Commi ee Aug 4, 2021 LEAD STAFF: Emily Ann Colby PRESENTED BY: Emily Ann Colby Ac on Item(s) # File Type Subcategory Item Descrip on 1 Ac on Se lement Approving the Workers' Compensa on claim of Mark Sauer by payment of $160,000 over three years to Mark Sauer and his a orneys Meuser Law Firm, and authorizing the City A orney's Office to execute any documents necessary to effectuate the se lement. Ward / Neighborhood / Address RCA-2021-00896 - Legal Settlement: Workers' Compensation claim of ... https://lims.minneapolismn.gov/RCA/8392 1 of 2 12/4/2021, 12:49 AM # Ward Neighborhood Address 1. Not Applicable Background Analysis City of Minneapolis employee sustained work-related ijureis. The par es reached a tenta ve se lement by payment of $160,000 over three years from fund 06930-1450100-789401-145400. Risk Management believes the se lement is in the best interests of the City and Rrecommends approval by the Commi ee and the City Council. FISCAL NOTE • Legal Se lement: Workers' Compensa on claim of Mark Sauer - Fiscal Note RCA-2021-00896 - Legal Settlement: Workers' Compensation claim of ... https://lims.minneapolismn.gov/RCA/8392 2 of 2 12/4/2021, 12:49 AM | C117: ["https://d3n8a8pro7vhmx.cloudfront.net/cuapb/pages/1462/attachments/original/1638637593/RCA-2021-00896_-_Legal_Settlement_Workers'_Compensation_claim_of_Mark_Sauer.pdf?1638637593"] | D117: ['Mark J. Sauer, badge #6308'] | E117: ['Department:Minneapolis Police Department'] | F117: 1414 | K117: =IF(Final_Cleaned_Data_V2!J117="Other", "Please specify here", "") | N117: =IF(Final_Cleaned_Data_V2!M117="Other", "Please specify here", "")
... A173: 252 | B173: Hennepin County 300 South Sixth Street, Minneapolis, MN 55487 DATE: February 18, 2022 TO: Deputy Samuel Fox FROM: Professional Standards Division RE: Written Reprimand You are receiving a written reprimand for your failure to follow Hennepin County's COVID-19 Vaccination and Testing Policy. Hennepin County has sent regular and ongoing communication regarding the policy expectation of being fully vaccinated or complying with weekly COVID testing. During the week of January 16-22, 2022 you failed to provide proof: • Of your vaccination status, or • That you had taken a COVID test and provided your test results Due to the seriousness of your failure to follow directives and abide by the county's vaccination and testing policy, you are being issued this written reprimand. It is my hope that you will take advantage of this opportunity to correct your behavior so that you may succeed in this position. Please note that continued incidents of this nature or a similar nature may result in additional, more serious disciplinary action up to and including termination. If you wish to appeal this action, your rights and the procedures are contained in the Labor Agreement between Hennepin County and the Minnesota Public Employees Association. Cc: Manager HR Business Partner Labor Relations Representative Payroll Contact Employee HR File | C173: ['https://assets.nationbuilder.com/cuapb/pages/1473/attachments/original/1671254317/20220218_Fox.pdf?1671254317'] | D173: ['Samuel Fox, badge #578'] | E173: ["Department:Hennepin County Sheriff's Department"] | F173: 1446 | K173: =IF(Final_Cleaned_Data_V2!J173="Other", "Please specify here", "") | N173: =IF(Final_Cleaned_Data_V2!M173="Other", "Please specify here", "")
A174: 253 | B174: Too_Long:Over 20 PagesOPCR Case #16-01727 PANEL RECOMMENDATION Page 2 of 3 Allegations 1. It is alleged that Officer Cape did not use reasonable judgement when handling the shotgun leading to the accidental discharge. (MPD P&P 5-105) CUAPB000735 OPCR Case #16-01727 PANEL RECOMMENDATION Page 3 of 3 Allegation #1: It is alleged that Officer Cape did not use reasonable judgement when handling the shotgun leading to the accidental discharge. Supportive Findings: YES NO REMAND SPLIT This allegation has merit. This allegation does not have merit. Remand to investigation for additional information. There is no majority vote. CUAPB000736 The panel finds merit with this allegation. Officer Cape failed to ensure the shotgun was completely unloaded, which created an unsafe condition resulting in an accidental discharge. The improper check of the chamber of the shotgun violates City Policy which states,"Employees shall use reasonable judgment in carrying out their duties and responsibilities. They need to weigh the consequences of their actions." Officer Cape's actions were unreasonable. Had Officer Cape properly checked the chamber of his shotgun prior to pulling the trigger, the discharge would not have occurred. Officer Cape admits to making a mistake and has received training to help prevent this from occurring again. | C174: ['https://d3n8a8pro7vhmx.cloudfront.net/cuapb/pages/270/attachments/original/1581619794/OPCR_case_16-01727_Cape.pdf?1581619794'] | D174: ['Charles Cape, badge #971'] | E174: ['Department:Minneapolis Police Department'] | F174: 1446 | G174: TRUE | K174: =IF(Final_Cleaned_Data_V2!J174="Other", "Please specify here", "") | N174: =IF(Final_Cleaned_Data_V2!M174="Other", "Please specify here", "")
A175: 254 | B175: Home >Legislative File 2021-01140 >RCA Legal se lement: Workers' Compensa on claim of Alan Williams (RCA-2021-01198) ORIGINATING DEPARTMENT Finance & Property Services To Commi ee(s) # Commi ee Name Mee ng Date 1 Policy & Government Oversight Commi ee Oct 20, 2021 LEAD STAFF: Emily Ann Colby PRESENTED BY: Emily Ann Colby Ac on Item(s) # File Type Subcategory Item Descrip on 1 Ac on Se lement Approving the se lement of the Workers' Compensa on claim of Alan Williams, by payment of $172,500 to Alan Williams and a orney, Meuser Law Firm, and authorizing the City A orney's Office to execute any documents necessary to effectuate the se lement. Previous Ac ons None RCA-2021-01198 - Legal settlement: Workers' Compensation claim of A... https://lims.minneapolismn.gov/RCA/8747 1 of 2 12/4/2021, 1:47 AM Ward / Neighborhood / Address # Ward Neighborhood Address 1. Not Applicable Background Analysis City of Minneapolis employee sustained work-related injuries. The par es reached a tenta ve se lement by payment of $172,500 over three years from fund 06930-1450100-789401-145400. Risk Management believes this se lement is in the best interests of the City and recommends approval by the Commi ee and the City Council. FISCAL NOTE • Legal se lement: Workers' Compensa on claim of Alan Williams - Fiscal Note RCA-2021-01198 - Legal settlement: Workers' Compensation claim of A... https://lims.minneapolismn.gov/RCA/8747 2 of 2 12/4/2021, 1:47 AM | C175: ["https://d3n8a8pro7vhmx.cloudfront.net/cuapb/pages/1462/attachments/original/1638637607/RCA-2021-01198_-_Legal_settlement_Workers'_Compensation_claim_of_Alan_Williams.pdf?1638637607"] | D175: ['Alan W. Williams, badge #7763'] | E175: ['Department:Minneapolis Police Department'] | F175: 1446 | K175: =IF(Final_Cleaned_Data_V2!J175="Other", "Please specify here", "") | N175: =IF(Final_Cleaned_Data_V2!M175="Other", "Please specify here", "")
A176: 255 | B176: MPR NEWS › Annotations Police ID St. Louis man shot by officers FEBRUARY ೄೇ, ೅ೃೄೆ St. Paul police have identified the man who was fatally shot by officers Tuesday after he stabbed a police dog. Alden Anderson, , of St. Louis was being sought by law enforcement on suspicion of first-degree criminal sexual conduct. Officers from St Paul, the North Star Fugitive Task Force, the Ramsey County Sheriff's Office, and US Marshals were aiding in the search. A police K- named Kody found Anderson in the basement of a Summit-University home, and Anderson stabbed the dog to death. St. Paul police spokesman Paul Paulos said Officer Jeffrey Thissen fired his weapon and has been placed on standard administrative leave. Two US Marshals also fired their weapons. A spokesperson for the Marshals Service said it does not identify officers. Paulos said there are no plans to publicly memorialize K- officer Kody. "We do let the handlers do their own thing; we consider the dogs one of their family members, so it is a private matter," Paulos said. The last time a St. Paul police dog was killed was , he said. Annotations · Report a problem COPY https://outline.com/GPDNVn ✕ HOME · TERMS · PRIVACY · DMCA · CONTACT Outline is a free service for reading and annotating news articles. We remove the clutter so you can analyze and comment on the content. In today's climate of widespread misinformation, Outline empowers readers to verify the facts. | C176: ['https://d3n8a8pro7vhmx.cloudfront.net/cuapb/pages/270/attachments/original/1626490928/Police_ID_St._Louis_man_shot_by_officers.pdf?1626490928'] | D176: ['Jeffrey C. Thissen, badge #679500'] | E176: ['Department:St. Paul Police Department'] | F176: 1446 | K176: =IF(Final_Cleaned_Data_V2!J176="Other", "Please specify here", "") | N176: =IF(Final_Cleaned_Data_V2!M176="Other", "Please specify here", "")
A177: 256 | B177: Hennepin County 300 South Sixth Street, Minneapolis, MN 55487 DATE: April 1, 2022 TO: Deputy Vladimir Litvinov FROM: Professional Standards Division RE: Written Reprimand You are receiving a written reprimand for your failure to follow Hennepin County's COVID-19 Vaccination and Testing Policy. Hennepin County has sent regular and ongoing communication regarding the policy expectation of being fully vaccinated or complying with weekly COVID testing. During the week of March 6-12, 2022 you failed to provide proof: • Of your vaccination status, or • That you had taken a COVID test and provided your test results Due to the seriousness of your failure to follow directives and abide by the county's vaccination and testing policy, you are being issued this written reprimand. It is my hope that you will take advantage of this opportunity to correct your behavior so that you may succeed in this position. Please note that continued incidents of this nature or a similar nature may result in additional, more serious disciplinary action up to and including termination. If you wish to appeal this action, your rights and the procedures are contained in the Labor Agreement between Hennepin County and the Minnesota Public Employees Association. Cc: Manager HR Business Partner Labor Relations Representative Payroll Contact Employee HR File | C177: ['https://assets.nationbuilder.com/cuapb/pages/1473/attachments/original/1671254234/20220401_Litvinov.pdf?1671254234'] | D177: ['Vladimir Litvinov, badge #622'] | E177: ["Department:Hennepin County Sheriff's Department"] | F177: 1446 | K177: =IF(Final_Cleaned_Data_V2!J177="Other", "Please specify here", "") | N177: =IF(Final_Cleaned_Data_V2!M177="Other", "Please specify here", "")
A178: 257 | B178: Home >Legislative File 2021-01143 >RCA Legal se lement: Workers' Compensa on claim of Jeremy Foster (RCA-2021-01195) ORIGINATING DEPARTMENT Finance & Property Services To Commi ee(s) # Commi ee Name Mee ng Date 1 Policy & Government Oversight Commi ee Oct 20, 2021 LEAD STAFF: Emily Ann Colby PRESENTED BY: Emily Ann Colby Ac on Item(s) # File Type Subcategory Item Descrip on 1 Ac on Se lement Approving the se lement of the Workers' Compensa on claim of Jeremy Foster, by payment of $175,000 to Jeremy Foster and a orney, Meuser Law Firm, and authorizing the City A orney's Office to execute any documents necessary to effectuate the se lement. Previous Ac ons None RCA-2021-01195 - Legal settlement: Workers' Compensation claim of J... https://lims.minneapolismn.gov/RCA/8744 1 of 2 12/4/2021, 1:41 AM Ward / Neighborhood / Address # Ward Neighborhood Address 1. Not Applicable Background Analysis City of Minneapolis employee sustained work-related injuries. The par es have reached a tenta ve se lement by payment of $175,000 over two years from fund 06930-1450100-789401-145400. Risk Management believes the se lement is in the best interests of the City and recommends approval by the Commi ee and the City Council. FISCAL NOTE • Legal se lement: Workers' Compensa on claim of Jeremy Foster - Fiscal Note RCA-2021-01195 - Legal settlement: Workers' Compensation claim of J... https://lims.minneapolismn.gov/RCA/8744 2 of 2 12/4/2021, 1:41 AM | C178: ["https://d3n8a8pro7vhmx.cloudfront.net/cuapb/pages/1462/attachments/original/1638637606/RCA-2021-01195_-_Legal_settlement_Workers'_Compensation_claim_of_Jeremy_Foster.pdf?1638637606"] | D178: ['Jeremy Foster, badge #2076'] | E178: ['Department:Minneapolis Police Department'] | F178: 1448 | K178: =IF(Final_Cleaned_Data_V2!J178="Other", "Please specify here", "") | N178: =IF(Final_Cleaned_Data_V2!M178="Other", "Please specify here", "")
A179: 258 | B179: Hennepin County 300 South Sixth Street, Minneapolis, MN 55487 DATE: February 18, 2022 TO: Deputy Mikale Clark FROM: Professional Standards Division RE: Written Reprimand You are receiving a written reprimand for your failure to follow Hennepin County's COVID-19 Vaccination and Testing Policy. Hennepin County has sent regular and ongoing communication regarding the policy expectation of being fully vaccinated or complying with weekly COVID testing. During the week of January 23-29, 2022 you failed to provide proof: • Of your vaccination status, or • That you had taken a COVID test and provided your test results Due to the seriousness of your failure to follow directives and abide by the county's vaccination and testing policy, you are being issued this written reprimand. It is my hope that you will take advantage of this opportunity to correct your behavior so that you may succeed in this position. Please note that continued incidents of this nature or a similar nature may result in additional, more serious disciplinary action up to and including termination. If you wish to appeal this action, your rights and the procedures are contained in the Labor Agreement between Hennepin County and the Minnesota Public Employees Association. Cc: Manager HR Business Partner Labor Relations Representative Payroll Contact Employee HR File | C179: ['https://assets.nationbuilder.com/cuapb/pages/1473/attachments/original/1671254317/20220218_Clark.pdf?1671254317'] | D179: ['Mikale Clark, badge #672'] | E179: ["Department:Hennepin County Sheriff's Department"] | F179: 1448 | K179: =IF(Final_Cleaned_Data_V2!J179="Other", "Please specify here", "") | N179: =IF(Final_Cleaned_Data_V2!M179="Other", "Please specify here", "")
A180: 259 | B180: Home >Legislative File 2021-01032 >RCA Legal se lement: Workers' Compensa on claim of Sco Creighton (RCA-2021-01080) ORIGINATING DEPARTMENT Finance & Property Services To Commi ee(s) # Commi ee Name Mee ng Date 1 Policy & Government Oversight Commi ee Sep 22, 2021 LEAD STAFF: Emily Ann Colby PRESENTED BY: Emily Ann Colby Ac on Item(s) # File Type Subcategory Item Descrip on 1 Ac on Se lement Approving the se lement of the Workers' Compensa on claim of Sco Creighton, by payment of $190,000 over three years to Sco Creighton and a orney, Meuser Law Firm, and authorizing the City A orney's Office to execute any documents necessary to effectuate the se lement. Previous Ac ons RCA-2021-01080 - Legal settlement: Workers' Compensation claim of S... https://lims.minneapolismn.gov/RCA/8610 1 of 2 12/4/2021, 1:09 AM none Ward / Neighborhood / Address # Ward Neighborhood Address 1. Not Applicable Background Analysis City employee sustained work-related injuries. The par es reached a tenta ve se lement by payment of $190,000 over three years from fund 06930-1450100-789401-145400. Risk Management believes this se lement is in the best interests of the City and recommends approval by the Commi ee and City Council. FISCAL NOTE • Legal se lement: Workers' Compensa on claim of Sco Creighton - Fiscal Note RCA-2021-01080 - Legal settlement: Workers' Compensation claim of S... https://lims.minneapolismn.gov/RCA/8610 2 of 2 12/4/2021, 1:09 AM | C180: ["https://d3n8a8pro7vhmx.cloudfront.net/cuapb/pages/1462/attachments/original/1638637602/RCA-2021-01080_-_Legal_settlement_Workers'_Compensation_claim_of_Scott_Creighton.pdf?1638637602"] | D180: ['Scott Creighton, badge #1331'] | E180: ['Department:Minneapolis Police Department'] | F180: 1448 | K180: =IF(Final_Cleaned_Data_V2!J180="Other", "Please specify here", "") | N180: =IF(Final_Cleaned_Data_V2!M180="Other", "Please specify here", "")
A181: 260 | B181: Home >Legislative File 2021-01040 >RCA Legal se lement: Workers' Compensa on claim of Michael Manley (RCA-2021-01070) ORIGINATING DEPARTMENT Finance & Property Services To Commi ee(s) # Commi ee Name Mee ng Date 1 Policy & Government Oversight Commi ee Sep 22, 2021 LEAD STAFF: Emily Ann Colby PRESENTED BY: Emily Ann Colby Ac on Item(s) # File Type Subcategory Item Descrip on 1 Ac on Se lement Approving se lement of the Workers' Compensa on claim of Michael Manley, by payment of $165,000 over three years to Michael Manley and a orney, Meuser Law Firm, and authorizing the City A orney's Office to execute any documents necessary to effectuate the se lement. Previous Ac ons RCA-2021-01070 - Legal settlement: Workers' Compensation claim of ... https://lims.minneapolismn.gov/RCA/8599 1 of 2 12/4/2021, 1:21 AM None Ward / Neighborhood / Address # Ward Neighborhood Address 1. Not Applicable Background Analysis City employee sustained work-related injuries. The par es have reached a tenta ve se lement by payment of $165,000 over three years from fund 06930-1450100-789401-145400. Risk Management believes the se lement is in the best interests of the City and recommends approval by the Commi ee and the City Council FISCAL NOTE • Legal se lement: Workers' Compensa on claim of Michael Manley - Fiscal Note RCA-2021-01070 - Legal settlement: Workers' Compensation claim of ... https://lims.minneapolismn.gov/RCA/8599 2 of 2 12/4/2021, 1:21 AM | C181: ["https://d3n8a8pro7vhmx.cloudfront.net/cuapb/pages/1462/attachments/original/1638637599/RCA-2021-01070_-_Legal_settlement_Workers'_Compensation_claim_of_Michael_Manley.pdf?1638637599"] | D181: ['Michael Manley, badge #4385'] | E181: ['Department:Minneapolis Police Department'] | F181: 1449 | K181: =IF(Final_Cleaned_Data_V2!J181="Other", "Please specify here", "") | N181: =IF(Final_Cleaned_Data_V2!M181="Other", "Please specify here", "")
A182: 261 | B182: Home >Legislative File 2021-01191 >RCA Legal se lement: Workers' Compensa on claim of John Transgrud (RCA-2021-01219) ORIGINATING DEPARTMENT Finance & Property Services To Commi ee(s) # Commi ee Name Mee ng Date 1 Policy & Government Oversight Commi ee Nov 3, 2021 LEAD STAFF: Emily Ann Colby PRESENTED BY: Emily Ann Colby Ac on Item(s) # File Type Subcategory Item Descrip on 1 Ac on Se lement Approving the se lement of the Workers' Compensa on claim of John Transgrud, by payment of $175,000 to John Transgrud and a orney, Meuser Law Firm, and authorizing the City A orney's Office to execute any documents necessary to effectuate the se lement. Previous Ac ons None RCA-2021-01219 - Legal settlement: Workers' Compensation claim of J... https://lims.minneapolismn.gov/RCA/8777 1 of 2 12/4/2021, 1:55 AM Ward / Neighborhood / Address # Ward Neighborhood Address 1. Not Applicable Background Analysis City of Minneapolis employee sustained work-related injuries. The par es reached a tenta ve se lement by payment of $175,000 over three years from fund 06930-1450100-789401-145400. Risk Management believes this se lement is in the best interests of the City and recommends approval by the Commi ee and the City Council. FISCAL NOTE • Legal se lement: Workers' Compensa on claim of John Transgrud - Fiscal Note RCA-2021-01219 - Legal settlement: Workers' Compensation claim of J... https://lims.minneapolismn.gov/RCA/8777 2 of 2 12/4/2021, 1:55 AM | C182: ["https://d3n8a8pro7vhmx.cloudfront.net/cuapb/pages/1462/attachments/original/1638637579/RCA-2021-01219_-_Legal_settlement_Workers'_Compensation_claim_of_John_Transgrud.pdf?1638637579"] | D182: ['John Trangsrud, badge #7293'] | E182: ['Department:Minneapolis Police Department'] | F182: 1449 | K182: =IF(Final_Cleaned_Data_V2!J182="Other", "Please specify here", "") | N182: =IF(Final_Cleaned_Data_V2!M182="Other", "Please specify here", "")
A183: 262 | B183: Home >Legislative File 2021-01188 >RCA Legal se lement: Workers' Compensa on claim of Anthony Olsen (RCA-2021-01213) ORIGINATING DEPARTMENT Finance & Property Services To Commi ee(s) # Commi ee Name Mee ng Date 1 Policy & Government Oversight Commi ee Nov 3, 2021 LEAD STAFF: Emily Ann Colby PRESENTED BY: Emily Ann Colby Ac on Item(s) # File Type Subcategory Item Descrip on 1 Ac on Se lement Approving the se lement of the Workers' Compensa on claim of Anthony Olsen, by payment of $175,000 to Anthony Olsen and a orney, Meuser Law Firm, and authorizing the City A orney's Office to execute any documents necessary to effectuate the se lement. Previous Ac ons None RCA-2021-01213 - Legal settlement: Workers' Compensation claim of A... https://lims.minneapolismn.gov/RCA/8770 1 of 2 12/4/2021, 1:53 AM Ward / Neighborhood / Address # Ward Neighborhood Address 1. Not Applicable Background Analysis City of Minneapolis employee sustained work-related injuries. The par es reached a tenta ve se lement by payment of $175,000, over three years, from fund 06930-1450100-789401-145400. Risk Management believes the se lement to be in the best interests of the City and recommends approval by the Commi ee and the City Council. FISCAL NOTE • Legal se lement: Workers' Compensa on claim of Anthony Olsen - Fiscal Note RCA-2021-01213 - Legal settlement: Workers' Compensation claim of A... https://lims.minneapolismn.gov/RCA/8770 2 of 2 12/4/2021, 1:53 AM | C183: ["https://d3n8a8pro7vhmx.cloudfront.net/cuapb/pages/1462/attachments/original/1638637578/RCA-2021-01213_-_Legal_settlement_Workers'_Compensation_claim_of_Anthony_Olsen.pdf?1638637578"] | D183: ['Anthony Olsen, badge #5282'] | E183: ['Department:Minneapolis Police Department'] | F183: 1449 | K183: =IF(Final_Cleaned_Data_V2!J183="Other", "Please specify here", "") | N183: =IF(Final_Cleaned_Data_V2!M183="Other", "Please specify here", "")
A184: 263 | B184: Home >Legislative File 2021-01192 >RCA Legal se lement: Workers' Compensa on claim of Charles White (RCA-2021-01233) ORIGINATING DEPARTMENT Finance & Property Services To Commi ee(s) # Commi ee Name Mee ng Date 1 Policy & Government Oversight Commi ee Nov 3, 2021 LEAD STAFF: Emily Ann Colby PRESENTED BY: Emily Ann Colby Ac on Item(s) # File Type Subcategory Item Descrip on 1 Ac on Se lement Approving the se lement of the Workers' Compensa on claim of Charles White, by payment of $185,000 to Charles White and a orney, Meuser Law Firm, and authorizing the City A orney's Office to execute any documents necessary to effectuate the se lement. Previous Ac ons None RCA-2021-01233 - Legal settlement: Workers' Compensation claim of C... https://lims.minneapolismn.gov/RCA/8788 1 of 2 12/4/2021, 1:56 AM Ward / Neighborhood / Address # Ward Neighborhood Address 1. Not Applicable Background Analysis City of Minneapolis employee sustained work-related injuries. The par es have reached a tenta ve se lement by payment of $185,000 over three years from fund 06930-1450100-789401-145400. Risk Management believes the se lement is in the best interests of the City and recommends approval by the Commi ee and the City Council. FISCAL NOTE • Legal se lement: Workers' Compensa on claim of Charles White - Fiscal Note RCA-2021-01233 - Legal settlement: Workers' Compensation claim of C... https://lims.minneapolismn.gov/RCA/8788 2 of 2 12/4/2021, 1:56 AM | C184: ["https://d3n8a8pro7vhmx.cloudfront.net/cuapb/pages/1462/attachments/original/1638637581/RCA-2021-01233_-_Legal_settlement_Workers'_Compensation_claim_of_Charles_White.pdf?1638637581"] | D184: ['Charles White, badge #7714'] | E184: ['Department:Minneapolis Police Department'] | F184: 1449 | K184: =IF(Final_Cleaned_Data_V2!J184="Other", "Please specify here", "") | N184: =IF(Final_Cleaned_Data_V2!M184="Other", "Please specify here", "")
A185: 264 | B185: Hennepin County 300 South Sixth Street, Minneapolis, MN 55487 DATE: March 9, 2022 TO: Deputy Alexandra Urgiles FROM: Professional Standards Division RE: Written Reprimand You are receiving a written reprimand for your failure to follow Hennepin County's COVID-19 Vaccination and Testing Policy. Hennepin County has sent regular and ongoing communication regarding the policy expectation of being fully vaccinated or complying with weekly COVID testing. During the week of February 13-19, 2022 you failed to provide proof: • Of your vaccination status, or • That you had taken a COVID test and provided your test results Due to the seriousness of your failure to follow directives and abide by the county's vaccination and testing policy, you are being issued this written reprimand. It is my hope that you will take advantage of this opportunity to correct your behavior so that you may succeed in this position. Please note that continued incidents of this nature or a similar nature may result in additional, more serious disciplinary action up to and including termination. If you wish to appeal this action, your rights and the procedures are contained in the Labor Agreement between Hennepin County and the Minnesota Public Employees Association. Cc: Manager HR Business Partner Labor Relations Representative Payroll Contact Employee HR File | C185: ['https://assets.nationbuilder.com/cuapb/pages/1473/attachments/original/1671254322/20220309_Urgiles.pdf?1671254322'] | D185: ['Alexandra Urgiles, badge #685'] | E185: ["Department:Hennepin County Sheriff's Department"] | F185: 1450 | K185: =IF(Final_Cleaned_Data_V2!J185="Other", "Please specify here", "") | N185: =IF(Final_Cleaned_Data_V2!M185="Other", "Please specify here", "")
A186: 265 | B186: Home >Legislative File 2021-01190 >RCA Legal se lement: Workers' Compensa on claim of Sco Sutherland (RCA-2021-01214) ORIGINATING DEPARTMENT Finance & Property Services To Commi ee(s) # Commi ee Name Mee ng Date 1 Policy & Government Oversight Commi ee Nov 3, 2021 LEAD STAFF: Emily Ann Colby PRESENTED BY: Emily Ann Colby Ac on Item(s) # File Type Subcategory Item Descrip on 1 Ac on Se lement Approving the se lement of the Workers' Compensa on claim of Sco Sutherland, by payment of $175,000 to Sco Sutherland and a orney, Meuser Law Firm, and authorizing the City A orney's Office to execute any documents necessary to effectuate the se lement. Previous Ac ons None RCA-2021-01214 - Legal settlement: Workers' Compensation claim of S... https://lims.minneapolismn.gov/RCA/8771 1 of 2 12/4/2021, 1:54 AM Ward / Neighborhood / Address # Ward Neighborhood Address 1. Not Applicable Background Analysis City of Minneapolis employee sustained work-related injuries. The par es reached a tenta ve se lement by payment of $175,000 over two years from fund 06930-1450100-789401-145400. Risk Management believes the se lement is in the best interests of the City and recommends approval by the Commi ee and the City Council. FISCAL NOTE • Legal se lement: Workers' Compensa on claim of Sco Sutherland - Fiscal Note RCA-2021-01214 - Legal settlement: Workers' Compensation claim of S... https://lims.minneapolismn.gov/RCA/8771 2 of 2 12/4/2021, 1:54 AM | C186: ["https://d3n8a8pro7vhmx.cloudfront.net/cuapb/pages/1462/attachments/original/1638637578/RCA-2021-01214_-_Legal_settlement_Workers'_Compensation_claim_of_Scott_Sutherland.pdf?1638637578"] | D186: ['Scott Sutherland, badge #7017'] | E186: ['Department:Minneapolis Police Department'] | F186: 1450 | K186: =IF(Final_Cleaned_Data_V2!J186="Other", "Please specify here", "") | N186: =IF(Final_Cleaned_Data_V2!M186="Other", "Please specify here", "")
... A224: 303 | B224: Hennepin County 300 South Sixth Street, Minneapolis, MN 55487 DATE: January 26, 2022 TO: Detention Deputy Travis Pounder FROM: Assistant County Administrator Mark Thompson RE: Written Reprimand You are receiving a written reprimand for your failure to follow Hennepin County's COVID-19 Vaccination and Testing Policy. Hennepin County has sent regular and ongoing communication regarding the policy expectation of being fully vaccinated or complying with weekly COVID testing. During the week of January 9-15, 2022 you failed to provide proof: • Of your vaccination status, or • That you had taken a COVID test and provided your test results Due to the seriousness of your failure to follow directives and abide by the county's vaccination and testing policy, you are being issued this written reprimand. It is my hope that you will take advantage of this opportunity to correct your behavior so that you may succeed in this position. Please note that continued incidents of this nature or a similar nature may result in additional, more serious disciplinary action up to and including termination. If you wish to appeal this action, your rights and the procedures are contained in the Labor Agreement between Hennepin County and the Minnesota Public Employees Association. Cc: Manager HR Business Partner Labor Relations Representative Payroll Contact Employee HR File | C224: ['https://assets.nationbuilder.com/cuapb/pages/1473/attachments/original/1671254315/20220126_Pounder.pdf?1671254315'] | D224: ['Travis Pounder, badge #None'] | E224: ["Department:Hennepin County Sheriff's Department"] | F224: 1471 | K224: =IF(Final_Cleaned_Data_V2!J224="Other", "Please specify here", "") | N224: =IF(Final_Cleaned_Data_V2!M224="Other", "Please specify here", "")
A225: 304 | B225: Too_Long:Over 20 PagesCASE 0:04-cv-02882-DWF-AJB Document 1 Filed 06/03/04 Page 1 of 21 CASE 0:04-cv-02882-DWF-AJB Document 1 Filed 06/03/04 Page 2 of 21 CASE 0:04-cv-02882-DWF-AJB Document 1 Filed 06/03/04 Page 3 of 21 CASE 0:04-cv-02882-DWF-AJB Document 1 Filed 06/03/04 Page 4 of 21 CASE 0:04-cv-02882-DWF-AJB Document 1 Filed 06/03/04 Page 5 of 21 CASE 0:04-cv-02882-DWF-AJB Document 1 Filed 06/03/04 Page 6 of 21 CASE 0:04-cv-02882-DWF-AJB Document 1 Filed 06/03/04 Page 7 of 21 CASE 0:04-cv-02882-DWF-AJB Document 1 Filed 06/03/04 Page 8 of 21 CASE 0:04-cv-02882-DWF-AJB Document 1 Filed 06/03/04 Page 9 of 21 CASE 0:04-cv-02882-DWF-AJB Document 1 Filed 06/03/04 Page 10 of 21 CASE 0:04-cv-02882-DWF-AJB Document 1 Filed 06/03/04 Page 11 of 21 CASE 0:04-cv-02882-DWF-AJB Document 1 Filed 06/03/04 Page 12 of 21 CASE 0:04-cv-02882-DWF-AJB Document 1 Filed 06/03/04 Page 13 of 21 CASE 0:04-cv-02882-DWF-AJB Document 1 Filed 06/03/04 Page 14 of 21 CASE 0:04-cv-02882-DWF-AJB Document 1 Filed 06/03/04 Page 15 of 21 CASE 0:04-cv-02882-DWF-AJB Document 1 Filed 06/03/04 Page 16 of 21 CASE 0:04-cv-02882-DWF-AJB Document 1 Filed 06/03/04 Page 17 of 21 CASE 0:04-cv-02882-DWF-AJB Document 1 Filed 06/03/04 Page 18 of 21 CASE 0:04-cv-02882-DWF-AJB Document 1 Filed 06/03/04 Page 19 of 21 CASE 0:04-cv-02882-DWF-AJB Document 1 Filed 06/03/04 Page 20 of 21 | C225: ['https://d3n8a8pro7vhmx.cloudfront.net/cuapb/pages/270/attachments/original/1625786744/Donald_Williams_case_-_2002.pdf?1625786744'] | D225: ['Geoffrey Toscano, badge #7257', 'Lucas Peterson, badge #5630'] | E225: ['Department:Minneapolis Police Department'] | F225: 1472 | G225: TRUE | K225: =IF(Final_Cleaned_Data_V2!J225="Other", "Please specify here", "") | N225: =IF(Final_Cleaned_Data_V2!M225="Other", "Please specify here", "")
A226: 305 | B226: Hennepin County 300 South Sixth Street, Minneapolis, MN 55487 DATE: January 13, 2022 TO: Detention Deputy Jacob Weldon FROM: Assistant County Administrator Mark Thompson RE: Written Reprimand You are receiving a written reprimand for your failure to follow Hennepin County's COVID-19 Vaccination and Testing Policy. Hennepin County has sent regular and ongoing communication regarding the policy expectation of being fully vaccinated or complying with weekly COVID testing. During the week of December 12-18, 2021 you failed to provide proof: • Of your vaccination status, or • That you had taken a COVID test and provided your test results Due to the seriousness of your failure to follow directives and abide by the county's vaccination and testing policy, you are being issued this written reprimand. It is my hope that you will take advantage of this opportunity to correct your behavior so that you may succeed in this position. Please note that continued incidents of this nature or a similar nature may result in additional, more serious disciplinary action up to and including termination. If you wish to appeal this action, your rights and the procedures are contained in the Labor Agreement between Hennepin County and the Minnesota Public Employees Association. Cc: Manager HR Business Partner Labor Relations Representative Payroll Contact Employee HR File | C226: ['https://assets.nationbuilder.com/cuapb/pages/1473/attachments/original/1671254313/20220113_Weldon.pdf?1671254313'] | D226: ['Jacob Weldon, badge #None'] | E226: ["Department:Hennepin County Sheriff's Department"] | F226: 1472 | K226: =IF(Final_Cleaned_Data_V2!J226="Other", "Please specify here", "") | N226: =IF(Final_Cleaned_Data_V2!M226="Other", "Please specify here", "")
A227: 306 | B227: Hennepin County 300 South Sixth Street, Minneapolis, MN 55487 DATE: December 14, 2021 TO: Detention Deputy Paris Woods FROM: Assistant County Administrator Mark Thompson RE: Written Reprimand You are receiving a written reprimand for your failure to follow Hennepin County's COVID-19 Vaccination and Testing Policy. Hennepin County has sent regular and ongoing communication regarding the policy expectation of being fully vaccinated or complying with weekly COVID testing. During the week of October 17-23, 2021 you failed to provide proof: • Of your vaccination status, or • That you had taken a COVID test and provided your test results Due to the seriousness of your failure to follow directives and abide by the county's vaccination and testing policy, you are being issued this written reprimand. It is my hope that you will take advantage of this opportunity to correct your behavior so that you may succeed in this position. Please note that continued incidents of this nature or a similar nature may result in additional, more serious disciplinary action up to and including termination. If you wish to appeal this action, your rights and the procedures are contained in the Labor Agreement between Hennepin County and the Minnesota Public Employees Association. Cc: Manager HR Business Partner Labor Relations Representative Payroll Contact Employee HR File | C227: ['https://assets.nationbuilder.com/cuapb/pages/1473/attachments/original/1671254307/20211214_Woods.pdf?1671254307'] | D227: ['Paris Woods, badge #None'] | E227: ["Department:Hennepin County Sheriff's Department"] | F227: 1472 | K227: =IF(Final_Cleaned_Data_V2!J227="Other", "Please specify here", "") | N227: =IF(Final_Cleaned_Data_V2!M227="Other", "Please specify here", "")
A228: 307 | B228: Hennepin County 300 South Sixth Street, Minneapolis, MN 55487 DATE: December 14, 2021 TO: Detention Deputy Cara Lange FROM: Assistant County Administrator Mark Thompson RE: Written Reprimand You are receiving a written reprimand for your failure to follow Hennepin County's COVID-19 Vaccination and Testing Policy. Hennepin County has sent regular and ongoing communication regarding the policy expectation of being fully vaccinated or complying with weekly COVID testing. During the week of November 14-20, 2021 you failed to provide proof: • Of your vaccination status, or • That you had taken a COVID test and provided your test results Due to the seriousness of your failure to follow directives and abide by the county's vaccination and testing policy, you are being issued this written reprimand. It is my hope that you will take advantage of this opportunity to correct your behavior so that you may succeed in this position. Please note that continued incidents of this nature or a similar nature may result in additional, more serious disciplinary action up to and including termination. If you wish to appeal this action, your rights and the procedures are contained in the Labor Agreement between Hennepin County and the Minnesota Public Employees Association. Cc: Manager HR Business Partner Labor Relations Representative Payroll Contact Employee HR File | C228: ['https://assets.nationbuilder.com/cuapb/pages/1473/attachments/original/1671254299/20211214_Lange.pdf?1671254299'] | D228: ['Cara Lange, badge #None'] | E228: ["Department:Hennepin County Sheriff's Department"] | F228: 1473 | K228: =IF(Final_Cleaned_Data_V2!J228="Other", "Please specify here", "") | N228: =IF(Final_Cleaned_Data_V2!M228="Other", "Please specify here", "")
A229: 308 | B229: Home >Legislative File 2021-00198 >RCA Legal Se lement: Workers' Compensa on claim of Tammy Persoon (RCA-2021-00170) ORIGINATING DEPARTMENT City Attorney's Of ce To Commi ee(s) # Commi ee Name Mee ng Date 1 Policy & Government Oversight Commi ee Feb 10, 2021 LEAD STAFF: Emily Colby PRESENTED BY: Jim Rowader Ac on Item(s) # File Type Subcategory Item Descrip on 1 Ac on Se lement Approving the Workers' Compensa on claim of Tammy Persoon by payment of $125,000 to Ms. Persoon and her a orney Meuser Law Firm and authorizing the City A orney's Office to execute any documents necessary to effectuate the se lement. Ward / Neighborhood / Address RCA-2021-00170 - Legal Settlement: Workers' Compensation claim of ... https://limsqa.minneapolismn.gov/RCA/7463 1 of 2 12/4/2021, 12:01 AM # Ward Neighborhood Address 1. Not Applicable Background Analysis Former police officer Tammy Persoon sustained an alleged work-related injury. The par es engaged in se lement discussions and a tenta ve se lement was reached by payment of $125,000 from Fund/Org 06930-1450100-789401-145400. The City A orney's Office and RIsk Management believe this se lement is in the best interests of the City and recommend approval by this Commi ee and the City Council. FISCAL NOTE • Legal Se lement: Workers' Compensa on claim of Tammy Persoon - Fiscal Note RCA-2021-00170 - Legal Settlement: Workers' Compensation claim of ... https://limsqa.minneapolismn.gov/RCA/7463 2 of 2 12/4/2021, 12:01 AM | C229: ["https://d3n8a8pro7vhmx.cloudfront.net/cuapb/pages/1462/attachments/original/1638637583/RCA-2021-00170_-_Legal_Settlement_Workers'_Compensation_claim_of_Tammy_Persoon.pdf?1638637583"] | D229: ['Tammy L. Persoon, badge #5559'] | E229: ['Department:Minneapolis Police Department'] | F229: 1473 | K229: =IF(Final_Cleaned_Data_V2!J229="Other", "Please specify here", "") | N229: =IF(Final_Cleaned_Data_V2!M229="Other", "Please specify here", "")
A230: 309 | B230: Hennepin County 300 South Sixth Street, Minneapolis, MN 55487 DATE: January 19, 2022 TO: Detention Deputy Regina Joyner FROM: Assistant County Administrator Mark Thompson RE: Written Reprimand You are receiving a written reprimand for your failure to follow Hennepin County's COVID-19 Vaccination and Testing Policy. Hennepin County has sent regular and ongoing communication regarding the policy expectation of being fully vaccinated or complying with weekly COVID testing. During the week of October 17-23, 2021 you failed to provide proof: • Of your vaccination status, or • That you had taken a COVID test and provided your test results Due to the seriousness of your failure to follow directives and abide by the county's vaccination and testing policy, you are being issued this written reprimand. It is my hope that you will take advantage of this opportunity to correct your behavior so that you may succeed in this position. Please note that continued incidents of this nature or a similar nature may result in additional, more serious disciplinary action up to and including termination. If you wish to appeal this action, your rights and the procedures are contained in the Labor Agreement between Hennepin County and the Minnesota Public Employees Association. Cc: Manager HR Business Partner Labor Relations Representative Payroll Contact Employee HR File | C230: ['https://assets.nationbuilder.com/cuapb/pages/1473/attachments/original/1671254314/20220119_Joyner.pdf?1671254314'] | D230: ['Regina Joyner, badge #None'] | E230: ["Department:Hennepin County Sheriff's Department"] | F230: 1474 | K230: =IF(Final_Cleaned_Data_V2!J230="Other", "Please specify here", "") | N230: =IF(Final_Cleaned_Data_V2!M230="Other", "Please specify here", "")
A231: 310 | B231: Hennepin County 300 South Sixth Street, Minneapolis, MN 55487 DATE: December 14, 2021 TO: Detention Deputy Taylor Perry FROM: Assistant County Administrator Mark Thompson RE: Written Reprimand You are receiving a written reprimand for your failure to follow Hennepin County's COVID-19 Vaccination and Testing Policy. Hennepin County has sent regular and ongoing communication regarding the policy expectation of being fully vaccinated or complying with weekly COVID testing. During the week of October 11-16, 2021 you failed to provide proof: • Of your vaccination status, or • That you had taken a COVID test and provided your test results Due to the seriousness of your failure to follow directives and abide by the county's vaccination and testing policy, you are being issued this written reprimand. It is my hope that you will take advantage of this opportunity to correct your behavior so that you may succeed in this position. Please note that continued incidents of this nature or a similar nature may result in additional, more serious disciplinary action up to and including termination. If you wish to appeal this action, your rights and the procedures are contained in the Labor Agreement between Hennepin County and the Minnesota Public Employees Association. Cc: Manager HR Business Partner Labor Relations Representative Payroll Contact Employee HR File | C231: ['https://assets.nationbuilder.com/cuapb/pages/1473/attachments/original/1671254303/20211214_Perry.pdf?1671254303'] | D231: ['Taylor Perry, badge #None'] | E231: ["Department:Hennepin County Sheriff's Department"] | F231: 1474 | K231: =IF(Final_Cleaned_Data_V2!J231="Other", "Please specify here", "") | N231: =IF(Final_Cleaned_Data_V2!M231="Other", "Please specify here", "")
A232: 311 | B232: Hennepin County 300 South Sixth Street, Minneapolis, MN 55487 DATE: December 14, 2021 TO: Detention Deputy Abdiaziz Omar FROM: Assistant County Administrator Mark Thompson RE: Written Reprimand You are receiving a written reprimand for your failure to follow Hennepin County's COVID-19 Vaccination and Testing Policy. Hennepin County has sent regular and ongoing communication regarding the policy expectation of being fully vaccinated or complying with weekly COVID testing. During the week of October 24-30, 2021 you failed to provide proof: • Of your vaccination status, or • That you had taken a COVID test and provided your test results Due to the seriousness of your failure to follow directives and abide by the county's vaccination and testing policy, you are being issued this written reprimand. It is my hope that you will take advantage of this opportunity to correct your behavior so that you may succeed in this position. Please note that continued incidents of this nature or a similar nature may result in additional, more serious disciplinary action up to and including termination. If you wish to appeal this action, your rights and the procedures are contained in the Labor Agreement between Hennepin County and the Minnesota Public Employees Association. Cc: Manager HR Business Partner Labor Relations Representative Payroll Contact Employee HR File | C232: ['https://assets.nationbuilder.com/cuapb/pages/1473/attachments/original/1671254301/20211214_Omar.pdf?1671254301'] | D232: ['Abdiaziz Omar, badge #None'] | E232: ["Department:Hennepin County Sheriff's Department"] | F232: 1474 | K232: =IF(Final_Cleaned_Data_V2!J232="Other", "Please specify here", "") | N232: =IF(Final_Cleaned_Data_V2!M232="Other", "Please specify here", "")
A233: 312 | B233: Hennepin County 300 South Sixth Street, Minneapolis, MN 55487 DATE: December 14, 2021 TO: Detention Deputy Samukai Dunna FROM: Assistant County Administrator Mark Thompson RE: Written Reprimand You are receiving a written reprimand for your failure to follow Hennepin County's COVID-19 Vaccination and Testing Policy. Hennepin County has sent regular and ongoing communication regarding the policy expectation of being fully vaccinated or complying with weekly COVID testing. During the week of November 7-13, 2021 you failed to provide proof: • Of your vaccination status, or • That you had taken a COVID test and provided your test results Due to the seriousness of your failure to follow directives and abide by the county's vaccination and testing policy, you are being issued this written reprimand. It is my hope that you will take advantage of this opportunity to correct your behavior so that you may succeed in this position. Please note that continued incidents of this nature or a similar nature may result in additional, more serious disciplinary action up to and including termination. If you wish to appeal this action, your rights and the procedures are contained in the Labor Agreement between Hennepin County and the Minnesota Public Employees Association. Cc: Manager HR Business Partner Labor Relations Representative Payroll Contact Employee HR File | C233: ['https://assets.nationbuilder.com/cuapb/pages/1473/attachments/original/1671254297/20211214_Dunna.pdf?1671254297'] | D233: ['Samukai Dunna, badge #None'] | E233: ["Department:Hennepin County Sheriff's Department"] | F233: 1475 | K233: =IF(Final_Cleaned_Data_V2!J233="Other", "Please specify here", "") | N233: =IF(Final_Cleaned_Data_V2!M233="Other", "Please specify here", "")
A234: 313 | B234: Hennepin County 300 South Sixth Street, Minneapolis, MN 55487 DATE: December 14, 2021 TO: Detention Deputy Scott Widell FROM: Assistant County Administrator Mark Thompson RE: Written Reprimand You are receiving a written reprimand for your failure to follow Hennepin County's COVID-19 Vaccination and Testing Policy. Hennepin County has sent regular and ongoing communication regarding the policy expectation of being fully vaccinated or complying with weekly COVID testing. During the week of November 21-27, 2021 you failed to provide proof: • Of your vaccination status, or • That you had taken a COVID test and provided your test results Due to the seriousness of your failure to follow directives and abide by the county's vaccination and testing policy, you are being issued this written reprimand. It is my hope that you will take advantage of this opportunity to correct your behavior so that you may succeed in this position. Please note that continued incidents of this nature or a similar nature may result in additional, more serious disciplinary action up to and including termination. If you wish to appeal this action, your rights and the procedures are contained in the Labor Agreement between Hennepin County and the Minnesota Public Employees Association. Cc: Manager HR Business Partner Labor Relations Representative Payroll Contact Employee HR File | C234: ['https://assets.nationbuilder.com/cuapb/pages/1473/attachments/original/1671254307/20211214_Widell.pdf?1671254307'] | D234: ['Scott Widell, badge #None'] | E234: ["Department:Hennepin County Sheriff's Department"] | F234: 1475 | K234: =IF(Final_Cleaned_Data_V2!J234="Other", "Please specify here", "") | N234: =IF(Final_Cleaned_Data_V2!M234="Other", "Please specify here", "")
A235: 314 | B235: KSTP › Annotations Man, officers involved in deadly confrontation in Robbinsdale identified JANUARY ೄೄ, ೅ೃ೅ೄ Meanwhile, the Minnesota Bureau of Criminal Apprehension identified the officers involved as: Sgt. Brian Sloat, a -year veteran of the Robbinsdale Police Department, and Officer John Tomczik, who's been with the department for over a year. The BCA said Tomczik only discharged his Taser while Sloat discharged his firearm. According to Robbinsdale Police, officers attempted a traffic stop on a vehicle in which the registered owner had an active felony warrant out for their arrest at about : a.m. Friday. A short pursuit ensued before the vehicle was disabled. Andren then got out of the vehicle while holding a knife. Police said Andren ignored several commands from officers to drop the knife, and attempts to use a Taser on him were unsuccessful. Police said Andren charged at officers with the knife "in an aggressive manner" and officers fired their guns at him in response. Lifesaving measures were attempted but Andren was pronounced dead at the scene. The BCA is leading the investigation, which remains ongoing. Annotations · Report a problem COPY https://outline.com/CymaPG HOME · TERMS · PRIVACY · DMCA · CONTACT Outline is a free service for reading and annotating news articles. We remove the clutter so you can analyze and comment on the content. In today's climate of widespread misinformation, Outline empowers readers to verify the facts. | C235: ['https://d3n8a8pro7vhmx.cloudfront.net/cuapb/pages/270/attachments/original/1626881762/Man__officers_involved_in_deadly_confrontation_in_Robbinsdale_identified.pdf?1626881762'] | D235: ['John Tomczik, badge #None'] | E235: ['Department:Robbinsdale Police Department'] | F235: 1475 | K235: =IF(Final_Cleaned_Data_V2!J235="Other", "Please specify here", "") | N235: =IF(Final_Cleaned_Data_V2!M235="Other", "Please specify here", "")
A236: 315 | B236: Hennepin County 300 South Sixth Street, Minneapolis, MN 55487 DATE: December 14, 2021 TO: Detention Deputy Sam Sarsfield FROM: Assistant County Administrator Mark Thompson RE: Written Reprimand You are receiving a written reprimand for your failure to follow Hennepin County's COVID-19 Vaccination and Testing Policy. Hennepin County has sent regular and ongoing communication regarding the policy expectation of being fully vaccinated or complying with weekly COVID testing. During the week of October 24-30, 2021 you failed to provide proof: • Of your vaccination status, or • That you had taken a COVID test and provided your test results Due to the seriousness of your failure to follow directives and abide by the county's vaccination and testing policy, you are being issued this written reprimand. It is my hope that you will take advantage of this opportunity to correct your behavior so that you may succeed in this position. Please note that continued incidents of this nature or a similar nature may result in additional, more serious disciplinary action up to and including termination. If you wish to appeal this action, your rights and the procedures are contained in the Labor Agreement between Hennepin County and the Minnesota Public Employees Association. Cc: Manager HR Business Partner Labor Relations Representative Payroll Contact Employee HR File | C236: ['https://assets.nationbuilder.com/cuapb/pages/1473/attachments/original/1671254305/20211214_Sarsfield.pdf?1671254305'] | D236: ['Sam Sarsfield, badge #None'] | E236: ["Department:Hennepin County Sheriff's Department"] | F236: 1475 | K236: =IF(Final_Cleaned_Data_V2!J236="Other", "Please specify here", "") | N236: =IF(Final_Cleaned_Data_V2!M236="Other", "Please specify here", "")
A237: 316 | B237: Hennepin County 300 South Sixth Street, Minneapolis, MN 55487 DATE: December 21, 2021 TO: Detention Deputy Guled Abdullahi FROM: Assistant County Administrator Mark Thompson RE: Written Reprimand You are receiving a written reprimand for your failure to follow Hennepin County's COVID-19 Vaccination and Testing Policy. Hennepin County has sent regular and ongoing communication regarding the policy expectation of being fully vaccinated or complying with weekly COVID testing. During the week of October 11-16, 2021 you failed to provide proof: • Of your vaccination status, or • That you had taken a COVID test and provided your test results Due to the seriousness of your failure to follow directives and abide by the county's vaccination and testing policy, you are being issued this written reprimand. It is my hope that you will take advantage of this opportunity to correct your behavior so that you may succeed in this position. Please note that continued incidents of this nature or a similar nature may result in additional, more serious disciplinary action up to and including termination. If you wish to appeal this action, your rights and the procedures are contained in the Labor Agreement between Hennepin County and the Minnesota Public Employees Association. Cc: Manager HR Business Partner Labor Relations Representative Payroll Contact Employee HR File | C237: ['https://assets.nationbuilder.com/cuapb/pages/1473/attachments/original/1671254309/20211221_Abdullahi.pdf?1671254309'] | D237: ['Guled Abdullahi, badge #706'] | E237: ["Department:Hennepin County Sheriff's Department"] | F237: 1476 | K237: =IF(Final_Cleaned_Data_V2!J237="Other", "Please specify here", "") | N237: =IF(Final_Cleaned_Data_V2!M237="Other", "Please specify here", "")
... A851: 930 | B851: MINNEAPOLIS POLICE DEPARTMENT INTERNAL AFFAIRS COMPLAINT FORM #3401 COMPLAINT INFORMATION INTERNAL AFFAIRS CASE NUMBER: 13-17432 CCN: DATE OF INCIDENT: 07/27/2013 TIME OF INCIDENT: 2325 hours LOCATION OF INCIDENT: HWY 61 and Innovation Rd. S., Cottage Grove, MN DATE OF COMPLAINT 7/15/2013 REFERRAL METHOD: SEX M❑F❑ RACE: DATE OF BIRTH: 13. A 3 -'- rs•nn - I B. t. CITY / STATE / ZIP: TELEPHONE: POLICY INFORMATION POLICIES ALLEGED TO BE VIOLATED: - the influence of alcohol, 5-105.2: Possession of dut wea on or other 'rearm w i e consuming alcohol, ACCUSED EMPLOYEELS1 NAME/BADGE: Officer Sean McTaggart, #4657 COMPLAINT ALLEGATIONS It is alleged that on July 27th of 2013, Officer McTaggart violated MPD Code of Ethics, 5-102, by operating a motor vehicle under the influen • • . • • • • • • • • . • • • • ii • • ii ._ • art was laced under arrest . 1e I •1 • I i It is alleged that Officer McTag art violated MPD Code of Conduct, 5-105.2, by being in possession of a firearm while consuming alcohol. RECOMMENDATION (Preliminary Cases Only) K Reckoning Period Expired Before Complaint was Filed K No Basis for Complaint K Closed Pending Further Information K Refer to Precinct with Coaching Documentation K Exceptionally Cleared 0 Policy Failure K Other COMPLAINANT S DATE 1 (20 ---1-2; COMMANDER RE• ,, DAT 1207896 MINNEAPOLIS POLICE DEPARTMENT INTERNAL AFFAIRS COMPLAINT FORM #3401 COMPLAINT INFORMATION INTERNAL AFFAIRS CASE NUMBER: 13-17432 CCN: DATE OF INCIDENT: 07/27/2013 TIME OF INCIDENT: 2325 hours LOCATION OF INCIDENT: HWY 61 and Innovation Rd. S., Cottage Grove, MN DATE OF COMPLAINT 7/15/2013 REFERRAL METHOD: SEX M❑F❑ RACE: DATE OF BIRTH: 13. A 3 -'- rs•nn - I B. . CITY / STATE / ZIP: TELEPHONE: POLICY INFORMATION POLICIES ALLEGED TO BE VIOLATED: - the influence of alcohol, 5-105.2: Possession of dut wea on or other 'rearm w i e consuming alcohol, ACCUSED EMPLOYEE(S) NAME/BADGE: Officer Sean McTaggart, #4657 COMPLAINT ALLEGATIONS It is alleged that on July 27th of 2013, Officer McTaggart violated MPD Code of Ethics, 5-102, by operating a motor vehicle under the influen • • . • • • • • • • • . • • • • li • • M T. fart was laced under arrest . •• • • • -• • io i It is alleged that Officer McTa art violated MPD Code of Conduct, 5-105.2, by being in possession of a firearm while consuming alcohol. RECOMMENDATION (Preliminary Cases Only) K Reckoning Period Expired Before Complaint was Filed K No Basis for Complaint K Closed Pending Further Information K Refer to Precinct with Coaching Documentation K Exceptionally Cleared 0 Policy Failure K Other COMPLAINANT SIG DATE ( 2 --ea '-.1 ; COMMANDER REVIEW: DAT 1207897 MINNEAPOLIS POLICE DEPARTMENT Internal Affairs Unit Administrative Case #13-17432 Sgt. Michael Heyer Date: October 25th, 2013 CASE BACKGROUND This case resulted from Officer Sean McTaggart being arrested for D.W.I. by the Cottage Grove Police Department, on July 27th, 2013. Officer McTaggart was processed at the Cottage Grove P.D. Officer McTaggart was administered a breath test on a DMT DataMaster G. Officer McTaggart's first subject sample registered at .172 A.C. The second sample registered at 180 A.C. with an ending reported value at .17 A.C. At the time of his arrest, Officer McTaggart was in possession on a loaded handgun and had a City of Mpls. issued P.B.T. in his vehicle. Officer McTaggart also presented his MPD identification card at the time he was stopped by a Cottage Grove police officer. CASE INVESTIGATION 1 1207898 On 7/29/13, I received this case for investigation from case involved Minneapolis Police Officers McTaggart 13.43 - Personnel Data 13.43 - Personnel Data 13.43 - Personnel Data The Officer Sean I received an e-mail from Sgt. Melissa Chiodo. The e-mail stated that on 07/28/13 at approximately 0140 hours, Sgt. Chiodo was notified by the desk officer that a Captain from Cottage Grove PD was on the phone and wanted to speak with a supervisor. Sgt. Chiodo took the call from a Captain Greg Rinzel, who was a Commander of the Patrol Division for Cottage Grove. Captain Rinzel notified Sgt. Chiodo that at 2307 hours on 7/27/13 one of his officers observed a vehicle driving erratically, tailgating and crossing over the lines and initiated a TLE. When the Officer made contact with the driver, the driver immediately ID's himself as a MPLS Police Officer. The Cottage Grove Officer observed a PBT sitting on the seat next to the driver and asked the driver if he had been drinking. The driver admitted to having three drinks. The Cottage Grove Officer asked the driver if he had given himself a PBT before driving and the driver said yes that he had blown a .05 and was good to drive. The Cottage Grove Officer told the driver that if the driver passed the Field Sobriety Tests he would let him leave. The driver refused to do all testing and was brought to the station and given an intoxilyzer where he blew a .17 on the first test and a .18 on the second test. The vehicle was towed. 2 1207899 The driver was Officer Sean McTaggart Badge # 4567 of the 13.43 - Personnel Data Captain Rinzel said what was disturbing was the fact that Officer McTaggart had a loaded Smith and Wesson .38 Special on his person during the DWI. Captain Rinzel said they still only issued him a citation for Misdemeanor DWI even though he was carrying a loaded firearm. Captain Rinzel said one other thing disturbed him; came to pick up Officer McTaggart from the police station and Officer Hofius made threats to the Cottage Grove Officer who arrested Officer McTaggart. 13.43 told the arresting Officer that he knows his name and would spread the word to other cops about the officer arresting a Minneapolis Police Officer. Officer McTaggart was released at approximately 0100 hours with a citation and his gun was released to 13.43 The PBT that was in Officer McTaggart's front seat was an Alcoa Sensor PBT Serial 13.43 Captain Rinzel believed the PBT was the property of MPD. Captain Rinzel asked Sgt. Chiodo to notify the Internal Affairs Unit about the arrest for him. On 7/29/13, I contacted Barb Post, the records coordinator at the Cottage Grove P.D. I informed her who I was and why I was calling. I asked her to e-mail me a copy of the arrest report for Officer McTaggart and left a message for Captain Rinzel to contact me. 3 1207900 On 7/30/13, I spoke with Captain Rinzel. I asked him if he could provide me with copies of the squad video of the incident and if I could retrieve the PBT recovered from the arrest. Captain Rinzel stated that he would have copies of the video made and that I could have the PBT. On 7/30/13, Sgt. Brad Simonson of the MPD IAU, informed me that he could recover the property for me. On 7/31/13, Sgt. Simonson gave me two, CD's and a P.B.T. The P.B.T. was an Intoximeters, Inc., Alco-Sensor IV, serial 13,37 an additional number on the unit was, Inside the case I observed four, blow pieces. Three were wrapped in plastic, one was unwrapped. The P.B.T., the case and the blow pieces were property inventoried. I went to the MPD Store and asked if they had records of the purchase of P.B.T.'s for the Department. I was informed that they did not. I called the Traffic Unit and spoke with Sgt. Lee and asked the same question. Their records did not go back far enough to check this unit. I then called the 3rd Pct. and asked if they had the P.B.T. in question recorded. Sgt. Olson, assigned to the 3rd Pct. Day Watch, informed me that he could not find the documentation I was looking for. I e-mailed Lt. Kingsbury and asked him if he could find documentation for the P.B.T. in question. Lt. Kingsbury later informed me that he could not locate any documentation for the P.B.T. 4 1207901 | C851: ['https://d3n8a8pro7vhmx.cloudfront.net/cuapb/pages/1461/attachments/original/1638329826/13-17432_McTaggart_Part_1.pdf?1638329826'] | D851: ['Sean McTaggart, badge #4657'] | E851: ['Department:Minneapolis Police Department'] | F851: 7908 | K851: =IF(Final_Cleaned_Data_V2!J851="Other", "Please specify here", "") | N851: =IF(Final_Cleaned_Data_V2!M851="Other", "Please specify here", "")
A852: 931 | B852: Too_Long:Over 20 PagesOPCR Case #14-20461 Claudia Kittock PANEL RECOMMENDATION Page 2 of 5 $OOHJDWLRQV ,QDSSURSULDWH /DQJXDJH _x0086_ &RPSODLQDQWV &ODXGLD .LWWRFN 0LQQHDSROLV 3DUN 5HFUHDWLRQ 6XSHULQWHQGHQW -D\QH 0LOOHU DQG 5D\PRQG 9LJLO DOOHJH DQ RIILFHU PDGH FRPPHQWV DERXW WKH PDOHV EHLQJ SDUW RI ³$O 4DHGD ´ ,QDSSURSULDWH /DQJXDJH _x0086_ &RPSODLQDQWV .LWWRFN 0LOOHU DQG 9LJLO DOOHJH WKH\ RYHUKHDUG 03' RIILFHUV XVH SURIDQLW\ ZKLOH LQWHUDFWLQJ ZLWK WKH XQNQRZQ EODFN PDOHV &RPSODLQDQWV DOOHJH WKH\ KHDUG DQ 03' RIILFHU UHIHU WR RQH RI WKH XQNQRZQ EODFN PDOHV DV D ³SLHFH RI VKLW ´ 7KH RIILFHUV DUH DOOHJHG WR KDYH WROG WKH XQNQRZQ EODFN PDOHV WKDW WKH\ FDQ¶W ³EULQJ WKHLU VKLW KHUH ´ 7KH &RPSODLQDQWV DOOHJH WKH RIILFHU FRQVWDQWO\ XVLQJ WKH ZRUG ³IXFN´ WKURXJKRXW WKH LQWHUDFWLRQ CUAPB004287 OPCR Case #14-20461 Claudia Kittock PANEL RECOMMENDATION Page 5 of 5 CUAPB004290 OFFICE OF POLICE CONDUCT REVIEW Investigative Report Complaint Number: 14-20461 Investigator Michael A Grostyan Officer (s) Christopher Guelcher (002513) Jurisdiction M.C. O. §§ 172.20 Date of Incident August 15, 2014 Complaint Filed October 04, 2014 CASE OVERVIEW A 911 call was received alleging that there was a group of young unknown black males fighting in Gold Medal Park. Officers responded to the fight call. Several complaints were made about the language overheard during the interaction. Complainants witnessed an interaction between officers and a group of unknown black males. Complainants alleged that an officer made a comment referencing "Al Qaeda," and officers used profanity. SUMMARY OF ALLEGATIONS Allegation: Inappropriate Language-Protected Class 1. Complainants Claudia Kittock, Minneapolis Park & Recreation Superintendent Jayne Miller, and Raymond Vigil allege an officer made comments about the males being part of "Al Qaeda." Allegation: Inappropriate Language 1. Complainants Kittock, Miller, and Vigil allege they overheard MPD officers use profanity while interacting with the unknown black males. Complainants allege they heard an MPD officer refer to one of the unknown black males as a "piece of shit." The officers are alleged to have told the unknown black males that they can't "bring their shit here." The Complainants allege the officer constantly using the word "fuck" throughout the interaction. EVIDENCE 1. Statements a) Complainant, Claudia Kittock b) Complainant, Park & Recreation Board Superintendent Jayne Miller c) Complainant, Raymond Vigil CUAPB004291 2 d) Officer Christopher Guelcher e) Officer Sherry Appledorn f) Officer John Archer, Minneapolis Park Police g) Sergeant Erika Christiansen 2. Records a) CAPRS Report b) VisiNet SUMMARY OF EVIDENCE Based on a review of the evidence gathered during the OPCR investigation, the following occurred: 1. On August 14, 2014, at approximately 20:14 a 911 call was received. The caller observed 6-8 unknown black adolescent males were involved in a physical fight at Gold Medal Park. The caller did not observe any weapons. 2. At approximately 20:23 officers responded to Gold Medal Park located at 2nd Street and 10th Avenue in Minneapolis, Minnesota. 3. The responding officers were Minneapolis Park Police Officer John Archer, Officer Christopher Guelcher, Officer Sherry Appledorn and Sergeant Erika Christensen. 4. All officers arrived at Gold Medal Park at approximately the same time. 5. MPD Officers engaged with the group of males near the park; the group was located near a red rental car. 6. Officers detained and pat searched the group of unknown black males. 7. Officers found a bottle of prescription narcotics in the rental car. 8. Officer Guelcher engaged with the group of unknown black males, while Sergeant Christiansen verified the rental car information. 9. Officer Appledorn stated she was also engaged with the group of unknown black males. 10. Complainants alleged they heard officers using profanity, and a male officer make a comment about "Al-Qaeda" While interacting with the unknown black males at Gold Medal Park. 11. Meanwhile, Officer John Archer encountered two of the unknown black males leaving the park. 12. One of the two unknown black males had a warrant and was transported to HCJ by Officer Archer. 13. The incident was closed at 21:44. CUAPB004292 3 DISCUSSION The Minneapolis Police Department's Policy and Procedure Manual states in part: 5-105 (15) PROFESSIONAL CODE OF CONDUCT Employees shall be decorous in their language and conduct. They shall refrain from actions or words that bring discredit to the Department. They shall also not use words or terms which hold any person, group or organization up to contempt. The use of such unacceptable terms is strictly forbidden. All three complainants stated they heard a comment about "Al-Qaeda." Complainant Claudia Kittock stated she heard from her sixth-floor balcony an officer state "[h]ow was I supposed to know you don't work for Al-fucking Qaida," Complainant Kittock stated the officer told the unknown black males "I don't care if you are green, blue, purple, or whatever color you are, [] if you are acting up, I am going to stop you." Complainant Raymond Vigil and his wife were walking their dog when the incident occurred. Complainant Vigil indicated he did hear an officer make a comment about "Al-Qaeda." Complainant Parks Superintendent Jayne Miller was on a ride-along with Park Police Officer John Archer. Complainant Miller stated she got out of the squad car to observe the incident. Complainant Miller stated she heard a male MPD officer told the unknown black males "[y]ou are probably part of Al-Qaida." Park Police Officer John Archer did not recall hearing a comment about Al-Qaeda. However, according to Archer he was dealing with two males who had left the group. Once Officer Archer learned one of the males had a warrant he transported him to jail. Officer Archer did not recall much of what was said during the incident. He did recall that Minneapolis Parks Superintendent, Complainant Miller, made a comment to him regarding comments made by other officers. Sergeant Erika Christianson did not recall any comments about "Al Qaeda." Officer Appledorn denied hearing any comments relating to "Al-Qaeda." In fact, Officer Appledorn stated that officers were unjustifiably being called racist, and one of the males called her a "racist bitch." She did not recall hearing any comments about "Al-Qaeda." Officer Guelcher stated that he may have made a comment that "we don't care if you are black, white, red, or yellow," and officers "got called here to a 9-1-1 call. We have ha job to do." Officer Appledorn recalled that she may have made a similar comment. Officer Guelcher admitted he made a comment about Al-Qaeda. Officer Guelcher stated that the context of the "Al-Qaeda" comment was taken out of context by the Complainants. He stated that when the unknown black males accused officers of harassing them, officers stated they were responding to a call and needed to ID the males. Officer Guelcher admitted that he told the unknown black males "Do I know who you are? Have I dealt with you? I do not know you. I do not know you from Adam. For all I know you might be a member of Al-Qaeda." Additionally, the Minneapolis Police Department's Policy and Procedure Manual states that: 5-105(10) PROFESSIONAL CODE OF CONDUCT: Employees shall not use indecent, profane or unnecessarily harsh language in the performance of official duties or in the presence of the public. All three Complainants indicate profanity was used. Both Complaints Kittock and Miller recalled hearing different forms of the word "fuck." According to Complainant Vigil, he heard CUAPB004293 | C852: ['https://d3n8a8pro7vhmx.cloudfront.net/cuapb/pages/270/attachments/original/1638762034/OPCR_14-20461_Guelcher_Part_3.pdf?1638762034'] | D852: ['Christopher Guelcher, badge #2513'] | E852: ['Department:Minneapolis Police Department'] | F852: 7928 | G852: TRUE | K852: =IF(Final_Cleaned_Data_V2!J852="Other", "Please specify here", "") | N852: =IF(Final_Cleaned_Data_V2!M852="Other", "Please specify here", "")
A853: 932 | B853: Minneapolis City of Lakes June 9, 2011 Police Department Timothy J. Dolan Chief of Police 350 South 5th Street - Room 130 Minneapolis MN 55415-1389 Office 612 673-2853 TTY 612 673-2157 Officer Geoffrey Johnson In-Service Training Minneapolis Police Department Officer Johnson, RE: IAU Case Number #10-259 . LETTER OF REPRIMAND The finding for IAU Case #10-259 is as follows: MPD P/P 3-712 Employees Late or Failing to Appear for Court...SUSTAINED (Category B) You will receive this Letter of Reprimand. This case will remain a B violation and can be used as progressive discipline for three years until 11/9/2013, which is from the date of incident. This case will remain in the IAU files per the retention period guidelines mandated by State Law. Be advised that any additional violations of Department Rules and Regulations may result in more severe disciplinary action up to and including discharge from employment. Sincerely, Timothy J. Dolan Chief of Police BY: Scott Gerlicher Deputy Chief of Professional Standards City information and Services www.ci.minneapolis.mn.us Affirmative Action Employer 1216203 Page 2 Officer Geoffrey Johnson Letter of Reprimand I, Officer Geoffrey Johnson, acknowledge receipt of this Letter of Reprimand. Officer Geo CC: Captain Doyle Personnel IAU ohn on Date of Receipt 1216204 MINNEAPOLIS POLICE DEPARTMENT INTERNAL AFFAIRS COMPLAINT FORM #3401 COMPLAINT INFORMATION INTERNAL AFFAIRS CASE NUMBER: 10-259 CCN: N/A DATE OF INCIDENT: 11/09/2010 TIME OF INCIDENT: 1300 hours LOCATION OF INCIDENT: Hennepin County Government Center DATE OF COMPLAINT 11/27/2010 REFERRAL METHOD: Coaching Doc. COMPLAINANTS NAME LAST FIRST MIDDLE SEX ro❑ F❑ RACE: DATE OF BIRTH: 13.43 - Personnel Data H• ME ADDR CITY / STATE / ZIP: TELEPHONE: 13.43 - Personnel Data POLICY INFORMATION POLICIES ALLEGED TO BE VIOLATED: 3-712 EMPLOYEES LATE OR FAILING TO APPEAR FOR COURT ACCUSED EMPLOYEE(S) NAMEBADGE: Officer G. Johnson #3386 COMPLAINT ALLEGATIONS without contacting for similar State v Norman, It is alleged that Officer Johnson failed to appear in response to a trial notice on 11/09/2010 the City Attorney's office with a legitimate reason for his absence after having been coached within the past twelve months. As a result of Officer Johnson's absence, the case at issue, dismissed. conduct was RECOMMENDATION (Preliminary Cases Only) K Reckoning Period Expired Before Complaint was K No Basis for Complaint K Closed Pending Further Information K Refer to Precinct with Coaching Documentation K Exceptionally Cleared K Policy Failure K Other Filed COMPLAINANT SIGNATURE 4er? / "-e......o., DATE )2 ./ /:.% COMMANDER REVIEW DATE 1216205 MINNEAPOLIS POLICE DEPARTMENT Internal Affairs Unit Administrative Case #I0-259 Sgt. Scott Zierden 01/21/2011 CASE BACKGROUND This administrative investigation was started after a complaint was received from 13.43 - Personnel Data of the Minneapolis City Attorney's Office. The complaint stated that Officer Geoffrey Johnson (#3386) had failed to appear for court on 11/09/2010 at 1300 hours pursuant to a trial notice. As a result of his nonappearance the case at issue, State v. Dandre Norman was dismissed. Department records show that Officer Johnson was coached on 09/09/2010 for another instance of failing to appear for court on 08/03/2010. CASE INVESTIGATION The Fifth Precinct subpoena logs maintained by the sergeants at the precinct were obtained for October 2010 in an effort to ascertain whether Officer Johnson had received the trial notice for the case at issue (retained in the MISCELLANEOUS section of the file). Those records show that a trial notice was delivered to Officer G. Malloy for the case at issue on 10/08/2010, but they provide no indication that Officer Johnson was given the trial notice. However, because the subpoena logs are not deemed authoritative, 1 1216206 it was necessary to determine whether Officer Johnson received the trial notice by asking him directly at his interview. Workforce Director records show that Officer Johnson used a sick day for 11/09/2010. Being sick could be a legitimate reason for missing court, however, the employee is still required to attempt to contact either the prosecuting authority or Court Liaison to inform them of the absence. Only the prosecutor or presiding judge in a case may excuse a witness from being absent from trial. When Officer Johnson was notified of his date and time to provide a statement for this investigation, notification was also sent to Lieutenant Dean Christiansen as Officer Johnson's supervisor. Lieutenant Christiansen responded in an e-mail to this investigator stating that Officer Johnson was marked sick the entire day of 11/09/2010 and that Officer Johnson "said he called in sick to the court liaison." Lieutenant Christiansen's e- mail will be retained in this file under the MISCELLANEOUS section. Ka yang from the Court Liaison was contacted for this investigation. In an unrecorded telephone call she stated that when an officer calls her office to report that they are sick and will miss court, she documents it. She stated that on 11/09/2010 her records showed that no officer called her office to report being sick. Case Statements Statement of Officer Geoffrey Johnson Officer Geoffrey Johnson provided a statement for this investigation on 01/10/2011. Officer Johnson has been with the Minneapolis Police Department for eleven years and is currently assigned as the 13.43 13.43 - Personnel Data 2 1216207 Officer Johnson acknowledged being coached in September of 2010 for missing court pursuant to a trial notice. Officer Johnson also acknowledged receiving a trial notice in October for the case at issue with a trial date of 11/09/2010. Officer Johnson stated that he did not appear for the trial on 11/09/2010 because he was sick that day. He called in to Sergeant Brian Anderson and left a message about his illness, however, he could not recall if he called either the City Attorney's office or Court Liaison about missing the trial. SUMMARY OF ALLEGATIONS AND INVESTIGATIVE SUMMARY Allegation # 1: It is alleged that Officer Geoffrey Johnson failed to appear for court pursuant to a trial notice on 11/09/2010 without notifying the Minneapolis City Attorney's Office or Court Liaison of his inability to attend, after having been coached for similar conduct within the previous twelve months, and that as a result of his absence the case at issue was dismissed. If this allegation is found to be true it would violate the following department policy: 3-712 EMPLOYEES LATE OR FAILING TO APPEAR FOR COURT (12/28/01) (A-B) Court Liaison personnel monitor court appearances and case dispositions for the MPD. Employees unable to attend court for legitimate reasons shall notify the agency issuing the Subpoena or Trial Notice on the first business day the conflict is known to exist. Unacceptable absences may include, but are not limited to, off- dut em lo ment local trainin• or childcare issues. 3 1216208 Investigative Summary • In September 2010 Officer Johnson was coached for failing to appear in court pursuant to a trial notice. • In October 2010 Officer Johnson received a trial notice for a trial on 11/09/2010. • Officer Johnson failed to appear for the trial. • As a result of his absence, the case was dismissed. • Workforce records show that Officer Johnson was sick on the day of the trial. • Officer Johnson stated that he notified his supervisor that he was ill, but that he could not recall if he contacted the City Attorney's office or the Court Liaison. • Ka Vang from Court Liaison confirmed that she did not receive notification from Officer Johnson regarding his illness on 11/09/2010. Respectfully Submitted, Sgt. Sc•tt Zierden Internal Affairs Unit 4 1216209 | C853: ['https://d3n8a8pro7vhmx.cloudfront.net/cuapb/pages/1461/attachments/original/1638147882/13-30492_Johnson.pdf?1638147882'] | D853: ['Geoffrey Johnson, badge #3386'] | E853: ['Department:Minneapolis Police Department'] | F853: 7955 | K853: =IF(Final_Cleaned_Data_V2!J853="Other", "Please specify here", "") | N853: =IF(Final_Cleaned_Data_V2!M853="Other", "Please specify here", "")
A854: 933 | B854: 4/11/2021 Cop Gets $585K After Colleagues Snooped on Her DMV Data | WIRED https://www.wired.com/story/minnesota-police-dmv-database-abuse/ 1/5 LOUISE MATSAKIS SECURITY 06.21.2019 03:47 PM Minnesota Cop Awarded $585K After Colleagues Snooped on Her DMV Data A jury this week finds that Minneapolis police officers abused their license database access. Dozens of other lawsuits have made similar claims. IN 2013, AMY Krekelberg received an unsettling notice from Minnesota's Department of Natural Resources: An employee had abused his access to a government driver's license database and snooped on thousands of people in the state, mostly women. Krekelberg learned that she was one of them. MARLIN LEVISON/STAR TRIBUNE/GETTY IMAGES 4/11/2021 Cop Gets $585K After Colleagues Snooped on Her DMV Data | WIRED https://www.wired.com/story/minnesota-police-dmv-database-abuse/ 2/5 When Krekelberg asked for an audit of accesses to her DMV records, as allowed by Minnesota state law, she learned that her information-which would include things like her address, weight, height, and driver's license pictures-had been viewed nearly 1,000 times since 2003, even though she was never under investigation by law enforcement. In fact, Krekelberg was law enforcement: She joined the Minneapolis Police Department in 2012, after spending eight years working elsewhere for the city, mostly as an officer for the Park & Recreation Board. She later learned that over 500 of those lookups were conducted by dozens of other cops. Even more eerie, many officers had searched for her in the middle of the night. Krekelberg eventually sued the city of Minneapolis, as well as two individual officers, for violating the Driver's Privacy Protection Act, which governs the disclosure of personal information collected by state motor-vehicle departments. Earlier this week, her case prevailed. On Wednesday, a jury awarded Krekelberg $585,000, including $300,000 in punitive damages from the two defendants, who looked up Krekelberg's information after she allegedly rejected their romantic advances, according to court documents. "I think that the jury's verdict shows that people do take privacy quite seriously and that they take women's privacy seriously," says Sarah St. Vincent, a surveillance and national security researcher at Human Rights Watch who attended the trial. She is studying similar cases across the country. Louise Matsakis covers Amazon, internet law, and online culture for WIRED. There have been dozens of lawsuits against Minneapolis and other Minnesota cities in recent years over alleged abuses of license databases. Most of the cases were settled out of court or dismissed; Krekelberg's is the only one to have gone to trial. Two of Krekelberg's lawyers, Sonia Miller-Van Oort and Jonathan Strauss, say that their client suffered harassment from her colleagues for years as the case proceeded, and that in at least one instance, other cops refused to provide Krekelberg with backup support. She now works a desk job. "We are disappointed in this verdict, but the city takes very seriously the importance of data privacy," says Susan L. Segal, the Minneapolis city attorney. She stressed that the police department's policies have changed in recent years. Minneapolis employees are now required 4/11/2021 Cop Gets $585K After Colleagues Snooped on Her DMV Data | WIRED https://www.wired.com/story/minnesota-police-dmv-database-abuse/ 3/5 to enter a reason when they search DMV records. Previously, to learn to use the database, officers were encouraged to "go back to work and look up some of [their] friends and family members," says Segal. "There was not this awareness." Minnesota did have at least one rare accountability measure in place: It kept a log of when the DMV database was searched, and citizens have the right to request their file. Without that digital trail, Krekelberg likely wouldn't have had the evidence to bring a case. In many other states, similar protections don't exist, even for more advanced technologies, like facial recognition software. Policies can differ greatly between police departments, says Kade Crockford, director of the Technology for Liberty program at the ACLU of Massachusetts. "There's virtually no uniformity," she says. That makes it difficult for citizens to know when their information has been improperly accessed by the government, which happens not infrequently. A 2016 investigation by the Associated Press found hundreds of instances where law enforcement officials misused confidential databases for personal purposes, like to dig up dirt on romantic partners, neighbors, and journalists. One Ohio officer ran checks on his ex-girlfriend, and pleaded guilty to stalking her. Two Miami-Dade officers looked up a reporter who published negative stories about their department. "I was a trooper for a long time and it was a common practice for troopers to run someone's name through the [Massachusetts criminal record] system for reasons besides law enforcement," Michael Szymanski, a former state trooper who was disciplined for abusing a police database, told CommonWealth Magazine in May. "I can't tell you how many times I saw troopers run their next-door neighbor through [the system], run their old girlfriends' names, or run someone who they're having a dispute with." The problem goes beyond DMV and criminal records databases. Law enforcement officials have also been caught abusing technology that allows them to monitor the location of people's cell phones. In April, a former Missouri sheriff was sentenced to six months in prison for tracking a judge and members of the State Highway Patrol. Employees at private tech companies have also abused their access to databases of sensitive user information. Uber settled a lawsuit with the New York attorney general in 2016 over its 4/11/2021 Cop Gets $585K After Colleagues Snooped on Her DMV Data | WIRED https://www.wired.com/story/minnesota-police-dmv-database-abuse/ 4/5 "God View" tool, which allowed employees to track the location of riders without their consent, including that of a Buzzfeed reporter. Employees at Snapchat also may have misused an internal tool to spy on users, according to a recent Motherboard investigation. More lawmakers have started advocating for data privacy regulations at the state and federal level, but those conversations have mostly focused on reining in big tech companies, rather than information that public employees can access. "It's very hard for people to get any kind of redress for privacy violations," St. Vincent says. More Great WIRED Stories Inside Backpage.com's vicious battle with the Feds Google Photos hacks to tame your picture overload The Cold War project that pulled climate science from ice How to stop robocalls-or at least slow them down Everything you want-and need-to know about aliens Î Want the best tools to get healthy? Check out our Gear team's picks for the best fitness trackers, running gear (including shoes and socks), and best headphones. 📩 Get even more of our inside scoops with our weekly Backchannel newsletter Louise Matsakis was a Staff Writer at WIRED covering Amazon, TikTok, and digital platforms. STAFF WRITER Featured Video 4/11/2021 Cop Gets $585K After Colleagues Snooped on Her DMV Data | WIRED https://www.wired.com/story/minnesota-police-dmv-database-abuse/ 5/5 Surgical Resident Breaks Down More Medical Scenes From Film & TV Annie Onishi, general surgery resident at Columbia University, takes a look at more emergency room and operating room scenes from a variety of television shows and movies and breaks down how accurate they really are. TOPICS PRIVACY LAW ENFORCEMENT DATABASES 1 Year of WIRED for $10. The news of the future, now. S U B S C R I B E Did I fail you teach you proper surgical technique? Did I fail you teach you proper surgical technique? Did I fail you teach you proper surgical technique? Did I fail you teach you proper surgical technique? | C854: ['https://d3n8a8pro7vhmx.cloudfront.net/cuapb/pages/270/attachments/original/1618168204/Cop_Gets__585K_After_Colleagues_Snooped_on_Her_DMV_Data___WIRED.pdf?1618168204'] | D854: ['Aaron Collins, badge #1259', 'Alan Liotta, badge #4196', 'Andrew P. Enriquez, badge #1802', 'Anna Hedberg, badge #2927', 'Antonio San Roman, badge #6123', 'Beth Mota (Letourneau), badge #4106', 'Blake Moua, badge #4882', 'Brian Cummings, badge #1360', 'Bryce Robinson, badge #6062', 'Carlos Baires Escobar, badge #275', 'Christopher Cushenbery, badge #1375', 'Christopher House, badge #3165', 'Daniel O. Horn, badge #212', 'David C. Elliott, badge #1755', 'David C. Neil, badge #4950', 'David Honican, badge #3135', 'Dennis Hamilton, badge #2610', 'Eric Faulconer, badge #1925', 'George J. Peltz, badge #5546', 'Jamiel Mohammad, badge #5150', 'Jarrod Silva, badge #6551', 'Jeffrey York, badge #7893', 'Jennifer Lazarchic (Goodmanson), badge #2319', 'John Staufenberg, badge #6765', 'Johnny Mercil, badge #4732', 'Joseph Haspert, badge #2791', 'Joshua P. Lynaugh, badge #415550', 'Kurt S. Indehar, badge #3209', 'Lucas Peterson, badge #5630', 'Mark Durand, badge #1627', 'Mark J. Gasior, badge #2228', 'Mark Wisocki, badge #7820', 'Matthew G. Olson, badge #5305', 'Matthew J. Koncar, badge #359000', 'Matthew J. McLean, badge #4635', 'Michael Pfaff, badge #5675', 'Oscar Macias, badge #4319', 'Patrick S. Reuben, badge #5969', 'Patrick Windus, badge #7802', 'Philip Alejandrino, badge #29', 'Robert W. Illetschko, badge #3200', 'Roland Hillstrom, badge #2986', 'Scott L. Grabowski, badge #2366', 'Sherral Schmidt (Miller-Graf), badge #4799', 'Steve Wuorinen, badge #7876', 'Thomas A. Lopez, badge #4238', 'Thomas Hendrickson, badge #2960', 'Timothy J. Mattsson, badge #4490', 'Todd D. Sauvageau, badge #6309', 'Tong S. Yang, badge #750407'] | E854: ['Department:Minneapolis Police Department', 'Department:St. Paul Police Department'] | F854: 7970 | K854: =IF(Final_Cleaned_Data_V2!J854="Other", "Please specify here", "") | N854: =IF(Final_Cleaned_Data_V2!M854="Other", "Please specify here", "")
A855: 934 | B855: 13 excessive force complaints against Minneapolis police officer involved in Terrence Franklin shooting Lucas Peterson, a highly decorated officer, faces scrutiny for fatal Uptown shooting. By Alejandra Matos and Matt McKinney Star Tribune July 1, 2013 - 8:58am https://www.startribune.com/13-excessive-force-complaints-against-minneapolis-cop-involved-in- shooting/213718651/ Kyndell Harkness The scene near 27th Street and Bryant Avenue S., where two Minneapolis police officers were shot.and a man was shot and killed. A woman claimed a police officer slammed her head against a wall, punched and kicked her in the torso. A man said he was beaten with a flashlight. A woman blamed an officer for restraining her boyfriend so violently that it killed him. Each of these people allege misconduct by Minneapolis police officer Lucas Peterson, a decorated cop who joined the force in 2000. Since then, he has been named in at least 13 excessive force complaints that so far have cost the city and other agencies more than $700,000 in settlements, court and city records show. His supervisors and fellow officers praise Peterson as a courageous and exemplary cop. Court records offer a different view - an officer whose aggressive methods frequently cross the line. The actions of Peterson and other officers have come under scrutiny as the Hennepin County attorney's office reviews whether police were justified in shooting Terrence Franklin in the basement of an Uptown house May 10. Two officers were wounded by gunfire in that confrontation. Sources said Peterson was the one who shot and killed Franklin, whose death prompted protest marches and pressure on Chief Janeé Harteau to release more details on the deadly encounter. Since 2006, the city has settled nine claims involving Peterson, more than any other officer over the past seven years. "It's very clear that this officer, over a period of time now, is not what this force needs, and it puts a black eye on the force and a black eye on the city," said Brett Buckner, a former Minneapolis NAACP official who called for Peterson's firing 11 years ago. Peterson's work history includes a letter of reprimand from 2008 for a policy violation, according to a department spokesperson. No further information was immediately available. His personnel file also reveals an officer revered by his peers and supervisors. He was named the officer of the year for the Fourth Precinct, which covers the city's North Side, in 2009, 2010 and 2012. He has twice been awarded the department's Medal of Valor, most recently last month. "He's kind of, in my opinion, what we wish every cop could be," said John Delmonico, president of the Police Officers Federation of Minneapolis. Delmonico said he's known Peterson since he was a kid growing up in south Minneapolis. Peterson's grandfather, father and uncle were all police officers. "Clearly it's in the family blood," Delmonico said. As for the city's payouts, Delmonico said there's no correlation between the city's decision to settle a case and the police officer's guilt. Each of the cases was reviewed by the department's internal affairs unit. Cases may also get reviewed by the Hennepin County attorney's office, a grand jury and, if civil rights allegations are made, the FBI. "I'm confident there [were] good checks and balances to determine if it was misconduct or not," he said. In the Franklin case, said Delmonico, "if Luke Peterson is the one who shot [Franklin], then he is a hero because he stopped him from shooting cops." Harteau and Peterson did not respond to requests for comment. Peterson, who became a Minneapolis police officer on Oct. 22, 2000, started out on the night shift in Southwest and then south Minneapolis, according to his personnel file. He was named to the Metro Gang Strike Force in 2006, but was one of the officers investigated three years later when the state Department of Public Safety shut the force down amid allegations that Strike Force members conducted improper searches, seized property without authorization and injured people who were not suspects. The unit's actions led to a $3 million settlement for victims of Strike Force misconduct. Peterson's work investigating gangs in north Minneapolis helped the department make several big arrests, according to his personnel file. He was first named the Fourth Precinct officer of the year in 2009. The first award cited Peterson's work, saying his street contacts helped police stop a gang shooting; capture a violent felon who had kidnapped, raped and tortured a woman; and led to the capture of a St. Paul drug dealer and gang member who had two handguns, a hand grenade, 9 kilos of marijuana and $3,300 in cash. He also acted quickly in the fall of 2009, using contacts he had developed to find a wanted felon who had escaped police hours earlier after pointing a gun at a Minneapolis police officer. That incident won him praise from the department's top leadership, including Harteau, then the deputy chief. He was awarded the Medal of Valor in 2006 for helping two other officers pursue a violent burglary suspect, who stabbed an officer and was killed by another. He won it again May 13 for actions in 2012. "Luke has been a great performer for the MPD," said Tim Dolan, who was Minneapolis chief from 2006 to 2012. Attorney Kenneth Udoibok said in the last four years, Peterson "stands out" as a cop who is not afraid to use force, at times excessive. Udoibok sued Peterson in 2011 on behalf of Bill Dumas, who claimed the officer, as part of the Strike Force, kicked and punched him when he was face down on the ground. The League of Minnesota Cities Insurance Trust settled the case for $15,000. "He's not the only cop going out and putting himself in these high-risk situations," Udoibok said. "But they don't get sued." In a complaint filed by Symone Taylor in 2006, Taylor alleges Peterson "slammed" her "head into the side of the building, causing injury to her head, cheek, and face. Plaintiff Taylor was further beaten, assaulted, thrown to the ground and viciously kicked in the torso and back." The case was settled in 2009 for $15,000. In 2006, Peterson and officer Mark Kaspszak struggled with Derrick Simmons after a traffic stop, according to a lawsuit filed by Johnson. Peterson wrote in a police report that Nancy Johnson, Simmons' partner, jumped on a police officer's back as he fought with Simmons, but a surveillance camera later showed Johnson didn't touch the officers. The city settled the two claims for $100,000. Stephen Smith, Johnson's attorney, was shocked that Peterson was still on the force. "At least slap him on the wrist," Smith said. "But I suppose I was assuming too much." In 2002, the Minneapolis NAACP called for the firing of Peterson and officer Mark Johnson after the death of Christopher Burns. On Nov. 1 of that year, the officers had responded to a reported domestic dispute between Burns and his fiancée, Bernadine McWhorter, when they put him in a neck hold that led to cardiac arrest, the complaint said. The Hennepin County medical examiner ruled Burns' death a homicide. In 2003, a grand jury determined that the officer's use of a neck hold was appropriate to subdue Burns, but in 2007, the city paid $300,000 to settle the excessive force lawsuit filed by McWhorter. Buckner, then the NAACP second vice president, told the Star Tribune at the time that "another black man has been killed at the hands of the Minneapolis Police Department." Now he's running for the City Council's 5th Ward seat. Buckner said, if elected, his first question to the chief would be about Peterson: "How soon is his locker going to get cleared out?" Matt McKinney is a reporter on the Star Tribune's state team. In 15 years at the Star Tribune, he has covered business, agriculture and crime. mckinney@startribune.com 612-673-7329 _mattmckinney | C855: ['https://d3n8a8pro7vhmx.cloudfront.net/cuapb/pages/270/attachments/original/1599978179/Lucas_Peterson_Article.pdf?1599978179'] | D855: ['Andrew Stender, badge #6791', 'Mark Durand, badge #1627', 'Ricardo Muro, badge #4899'] | E855: ['Department:Minneapolis Police Department'] | F855: 7978 | K855: =IF(Final_Cleaned_Data_V2!J855="Other", "Please specify here", "") | N855: =IF(Final_Cleaned_Data_V2!M855="Other", "Please specify here", "")
A856: 935 | B856: Skip to Main Content Logout My Account Search Menu New Criminal/Traffic/Petty Search Refine Search Back Location : All MNCIS Sites - Case Search Help R A C N . 09-CR-11-621 The State of Minnesota vs Travis William Lindberg § § § § § § Case Type: Crim/Traf Mandatory Date Filed: 03/29/2011 Location: Carlton Judicial Officer: Macaulay, Robert E., Jr. P I Lead Attorneys Defendant Lindberg, Travis William Male DOB: 08/29/1978 Cloquet, MN 55720 Jurisdiction State of Minnesota NICHOLE JEAN CARTER 218-726-2323(W) C I Charges: Lindberg, Travis WilliamStatute Level Date Disposition Level of Sentence 1. Domestic Assault - By Strangulation 609.2247.2 Felony 03/27/201108/01/2011 Convicted 08/01/2011 Conviction deemed a Misdemeanor pursua 2. Domestic Assault-Misdemeanor- Intentionally Inflicts/Attempts to Inflict Bodily Harm 609.2242.1(2)Misdemeanor03/27/201108/01/2011 Dismissed E O C DISPOSITIONS 05/09/2011 Plea (Judicial Officer: Macaulay, Robert E., Jr.) 1. Domestic Assault - By Strangulation Not guilty 2. Domestic Assault-Misdemeanor-Intentionally Inflicts/Attempts to Inflict Bodily Harm Not guilty 06/06/2011 Amended Plea (Judicial Officer: Macaulay, Robert E., Jr.) Reason: Plea withdrawn by defendant, Plea agreement 1. Domestic Assault - By Strangulation Guilty 08/01/2011 Disposition (Judicial Officer: Macaulay, Robert E., Jr.) 1. Domestic Assault - By Strangulation Convicted 2. Domestic Assault-Misdemeanor-Intentionally Inflicts/Attempts to Inflict Bodily Harm Dismissed 08/01/2011 Stay of Imposition Pursuant to M.S. 609.135 1. Domestic Assault - By Strangulation 03/27/2011 (FEL) 609.2247.2 (60922472) Monitoring - Adult: Type: Supervised probation Agency: Carlton County Probation Term of 3 Yr 08/01/2011 - 08/01/2014 Status: Closed 08/13/2013 Local Confinement: Agency: Carlton County Jail Term: 90 Days Time To Serve: 90 Days Stay 0 Yr 0 Mo 0 Days Credit For Time Served: 3 Days Comment: *serve 1st 45 days jail as arranged by Probation, balance of 45 days staggered - Review/Report on December 5, 2011 at 9 - if in full compliance will not have to serve balance, if not be prepared to serve balance Status: Active 08/01/2011 Condition - Adult: 1. Pay restitution, $782.00 08/01/2011, Active 08/01/2011 2. Complete Chemical Assessment, 08/01/2011, Active 08/01/2011 3. Follow recommendations of evaluation, 08/01/2011, Active 08/01/2011 4. Anger management, DAIP or it's equivalent 08/01/2011, Active 08/01/2011 5. No alcohol/controlled substance use, 08/01/2011, Active 08/01/2011 6. No possession of alcohol or drugs, 08/01/2011, Active 08/01/2011 Firefox https://pa.courts.state.mn.us/CaseDetail.aspx?CaseID=1614377342 1 of 3 12/5/2022, 1:41 AM 7. Random testing, 08/01/2011, Active 08/01/2011 8. No same or similar, 08/01/2011, Active 08/01/2011 9. Domestic No Contact (DANCO), 08/01/2011 - 08/01/2014, Active 08/01/2011 10. No contact with victim(s), 08/01/2011, Active 08/01/2011 11. Supply DNA sample, 08/01/2011, Active 08/01/2011 12. Submit to Random Searches, submit at any time to an unannouced visit and/or warrantless search of my person, vehicle, or prem by Probation Officer or designee 08/01/2011, Active 08/01/2011 13. Contact with probation, 08/01/2011, Active 08/01/2011 14. Follow all instructions of probation, 08/01/2011, Active 08/01/2011 15. Sign Probation Agreement, 08/01/2011, Active 08/01/2011 16. Restitution reserved, 08/01/2011, Active 08/01/2011 17. Do not ship/transport/possess or receive firearm or ammo, 08/01/2011, Active 08/01/2011 18. Make all future court appearances, 08/01/2011, Active 08/01/2011 19. No violations of an Order for Protection, 08/01/2011, Active 08/01/2011 Fee Totals: Law Library Fees $10.00 County/Sheriff & Felony Fines $500.00 Crim/Traffic Surcharge (once per case) $75.00 Public Defender Co- Payment $75.00 Restitution $782.00 Fee Totals $ $1,442.00 Level of Sentence: Conviction deemed a Misdemeanor pursuant to M.S. 609.13 OTHER EVENTS AND HEARINGS 03/29/2011 Complaint-Order for Detention (Judicial Officer: Wolf, Dale Albert ) 03/29/2011 Bail Hearing (11:15 AM) (Judicial Officer Wolf, Dale Albert) Result: Held 03/29/2011 Statement of Rights (Judicial Officer: Wolf, Dale Albert ) 03/29/2011 Application for Public Defender (Judicial Officer: Wolf, Dale Albert ) 03/29/2011 Order Granting Public Defender (Judicial Officer: Wolf, Dale Albert ) 03/29/2011 Interim Condition for Lindberg, Travis William - Pay bail $1,000.00 - Domestic No Contact (DANCO) 03/29/2011 Criminal Domestic Abuse No Contact Order DANCO Pretrial (Judicial Officer: Wolf, Dale Albert ) 03/29/2011 Review DANCO Expiration (Judicial Officer: Wolf, Dale Albert ) 03/29/2011 Order-Other (Judicial Officer: Wolf, Dale Albert ) 03/31/2011 Other Document 04/06/2011 Initial Appearance - Rule 8 (9:00 AM) (Judicial Officer Wolf, Dale Albert) Result: Held 04/06/2011 Demand for Omnibus Hearing (Judicial Officer: Wolf, Dale Albert ) 04/06/2011 Waiver (Judicial Officer: Wolf, Dale Albert ) 04/06/2011 Motion (Judicial Officer: Wolf, Dale Albert ) 04/06/2011 Order Granting Motion (Judicial Officer: Wolf, Dale Albert ) 04/06/2011 Interim Condition for Lindberg, Travis William - Pay bail $1,000.00 - Domestic No Contact (DANCO) 04/25/2011 Omnibus Hearing (9:00 AM) (Judicial Officer Wolf, Dale Albert) Result: Held 04/25/2011 Request for Continuance (Judicial Officer: Wolf, Dale Albert ) 05/09/2011 Omnibus Hearing (9:00 AM) (Judicial Officer Macaulay, Robert E., Jr.) Result: Held 05/09/2011 Omnibus Hearing Waived (Judicial Officer: Macaulay, Robert E., Jr. ) 05/18/2011 Demand-Speedy Trial 06/06/2011 Plea Hearing (9:00 AM) (Judicial Officer Macaulay, Robert E., Jr.) Result: Held 06/06/2011 Plea Agreement (Judicial Officer: Macaulay, Robert E., Jr. ) 06/06/2011 Petition to Enter Guilty Plea (Judicial Officer: Macaulay, Robert E., Jr. ) 06/06/2011 Order-Presentence Investigation (Judicial Officer: Macaulay, Robert E., Jr. ) 06/06/2011 Order-Chemical Dependency Evaluation (Judicial Officer: Macaulay, Robert E., Jr. ) 06/06/2011 Waiver of Jury Trial (Judicial Officer: Macaulay, Robert E., Jr. ) 06/06/2011 Withdrawal of Speedy Trial Demand (Judicial Officer: Macaulay, Robert E., Jr. ) 06/07/2011 Affidavit for Restitution 06/21/2011 Chemical Dependency Evaluation Report 06/28/2011 CANCELED Jury Trial (8:30 AM) (Judicial Officer Macaulay, Robert E., Jr.) Settled 07/15/2011 Request for Continuance 07/21/2011 Presentence Investigation Report 07/21/2011 Sentencing Worksheet 08/01/2011 Sentencing (9:00 AM) (Judicial Officer Macaulay, Robert E., Jr.) 07/18/2011 Continued to 08/01/2011 - By agreement - State of Minnesota Result: Held Firefox https://pa.courts.state.mn.us/CaseDetail.aspx?CaseID=1614377342 2 of 3 12/5/2022, 1:41 AM 08/01/2011 Victim Impact Statement (Judicial Officer: Macaulay, Robert E., Jr. ) 08/01/2011 Felony Conviction Sent to Secretary of State 08/01/2011 Criminal Domestic Abuse No Contact Order DANCO Probationary (Judicial Officer: Macaulay, Robert E., Jr. ) 08/01/2011 Payment Plan 08/01/2011 Sentencing Order (Judicial Officer: Macaulay, Robert E., Jr. ) 08/01/2011 Criminal Judgment and Warrant of Commitment (Judicial Officer: Macaulay, Robert E., Jr. ) 12/05/2011 Review Hearing (9:00 AM) (Judicial Officer Macaulay, Robert E., Jr.) Result: Held 12/05/2011 Order-Other (Judicial Officer: Macaulay, Robert E., Jr. ) 08/13/2013 Discharge from Probation or Monitoring (Judicial Officer: Macaulay, Robert E., Jr. ) 08/13/2013 Restoration of Voting Rights Sent to SOS 08/13/2013 Memorandum F I Defendant Lindberg, Travis William Total Financial Assessment 1,442.00 Total Payments and Credits 1,442.00 Balance Due as of 12/05/2022 0.00 08/01/2011 Transaction Assessment 1,442.00 10/17/2011 Counter Payment Receipt # 0009-2011-04526 Lindberg, Travis William (200.00) 11/22/2011 Counter Payment Receipt # 0009-2011-04998 Lindberg, Travis William (242.00) Firefox https://pa.courts.state.mn.us/CaseDetail.aspx?CaseID=1614377342 3 of 3 12/5/2022, 1:41 AM | C856: ['https://assets.nationbuilder.com/cuapb/pages/1472/attachments/original/1670226644/Lindberg_Conviction_Register_of_Actions.pdf?1670226644'] | D856: ['Travis Lindberg, badge #None'] | E856: ['Department:Babbitt Police Department'] | F856: 8053 | K856: =IF(Final_Cleaned_Data_V2!J856="Other", "Please specify here", "") | N856: =IF(Final_Cleaned_Data_V2!M856="Other", "Please specify here", "")
A857: 936 | B857: Minneapolis City of Lakes Police Department Timothy J. Dolan Chief of Police 350 South 5th Street - Room 130 Minneapolis MN 55415-1389 Office 612 673-2853 TTY 612 673-2157 Officer David Elliott Fourth Precinct Minneapolis Police Department Officer Elliott, September 27, 2011 RE: IAU Case Number #11-29 LETTER OF REPRIMAND The finding for IAU Case #11-29 is as follows: MPD P/P 3-801 Off-Duty (Outside) Employment...SUSTAINED (Category B) You will receive this Letter of Reprimand. This case will remain a B violation and can be used as progressive discipline for three years until January 2013, which is from the date of incident. The case will remain in the IAU files per the record retention guidelines mandated by State Law. Be advised that any additional violations of Department Rules and Regulations may result in more severe disciplinary action up to and including discharge from employment. Sincerely, Timothy J. Dolan Chief of Police City Information and Services Janee Harteau Assistant Chief of Police vivm.ci.minneapolis.mn.us Affirmative Action Employer 1212216 Page 2 Officer David Elliott Letter of Reprimand I, Officer David Elliott, acknowledge receipt of this Letter of Reprimand. Officer David Elliott Date of Receipt Inspector Martin CC: Inspector Martin Personnel IAU Date 1212217 MINNEAPOLIS POLICE DEPARTMENT INTERNAL AFFAIRS COMPLAINT FORM #3401 COMPLAINT INFORMATION INTERNAL AFFAIRS CASE NUMBER 11-29 LOCATION OF INCIDENT: Various Locations COMPLAINANTS NAME (LAST, FIRST MIDDLE) SEX RACE: DATE OF BIRTH: 13.43 M❑ Fp HOME ADDRESS CITY / STATE / ZIP TELEPHONE: CCN N/A DATE OF INCIDENT Jan 2010-Present TIME OF INCIDENT: Various Times DATE OF COMPLAINT 1/27/2011 REFERRAL METHOD: Internal POLICY INFORMATION POLICIES ALLEGED TO BE VIOLATED 3-801 Off-Duty (Outside) Employment ACCUSED EMPLOYEE(S) NAMEJBADGE Officer David Elliott # 1755 COMPLAINT ALLEGATIONS During the course of IAU Case 11-28, it was found that Officer Elliott consistently worked part time employment during 2010 and he did not submit an off-duty employment application required per policy to work off-duty. Officer Elliott is currently working off-duty and still has not complied with the off-duty policy or Administrative Announcement A11-012 that was issued on 3/9/2011. RECOMMENDATION (Preliminary Cases Only) K Reckoning Period Expired Before Complaint was Filed K No Basis for Complaint K Closed Pending Further Information K Refer to Precinct with Coaching Documentation K Exceptionally Cleared K Policy Failure K Other COM COM DI /1 ueur a c. ATI IOC DATE oS /7 - DATE 1212218 MINNEAPOLIS POLICE DEPARTMENT Internal Affairs Unit Administrative Case #11-29 Sgt. Melissa Chiodo June 27, 2011 CASE BACKGROUND While investigating IAU Case 11-28 I learned that Officer Elliott works off-duty as a Minneapolis Police Officer on a weekly basis but had not submitted the off-duty employment application required per MPD policy 3-801. I ran a Work Force Director Audit on Officer David Elliott searching for any applications and approval for him to work off-duty from 01/01/2005 - 12/31/2010. The report shows that Officer Elliott did not apply for any off-duty jobs during that period. From the period 01/01/2011 - 03/10/2011 Officer Elliott still had not submitted any off-duty applications. On 03/10/2011, Officer Elliott improperly submitted into Workforce Director an off-duty application for an unknown job working 1 day a week and it was rejected. 1 1212219 On 5/19/2011, Officer Elliott received his IAU notification letter for his Garrity statement regarding this case, on 5/30/2011, he submitted an off-duty application to work at 13.43 6 times weekly, and it was approved on 6/01/2011. 13.43 I ran an audit of Officer Elliott in Visnet for 2010 and 2011 and it showed that he was working off-duty on a regular basis in 2010 and 2011. I ran Officer Elliott prior to 2009 in Visinet but those records no longer exist. The Visinet audit revealed that Officer Elliott worked part time and used several different calls signs at unknown off-duty jobs and locations. I spoke with Greg Nelson, a supervisor in 911 about call signs used for part time. Greg confirmed that when an off-duty job does not have a regularly assigned call number the Channel 7 dispatcher would assign one to the officer based on the precinct they are working in. Precinct 4 would be the 6480 series; Precinct 5 would be 6580 series etc. He said that 13.43 - Personnel Data does not have a regular call sign and dispatch assigns one when an officer calls in for off-duty. During Officer Elliott's Garrity Statement I asked what part time jobs he works and he said 13.43 - Personnel Data According to Visinet Officer Elliott also works 13.43 - Personnel Data 13.43 - Personnel Data Elliott worked in 2010 and 2011 at 13.43 I also found that Officer 13.43 - Personnel Data off duty #6580 on 2 1212220 He also worked off-duty jobs that seemed to be a one-time job such as the 13.43 13.43 . None of these jobs had off-duty applications for Officer Elliott in 2010 and only 13.43 - Personnel Data does since June of 2011. I listened to the radio traffic and found that Officer Elliott usually called into Channel 7 when he worked part time to get a call number assigned to him and he called in to dispatch regularly to work at Officer Elliott Statement 13.43 - Personnel Data CASE STATEMENTS I asked Officer Elliot where he works off-duty and said he works off-duty at 13.43 - Personnel Data 13.43 He did not mention any other jobs. Officer Elliott admitted he worked the job all of 2010 and the beginning of 2011 without submitting an off-duty application and said it was because he forgot. In March 2011, Officer Elliott said he submitted an application to work off-duty on-line and it was rejected, he later resubmitted it and it was approved. 3 1212221 SUMMARY OF ALLEGATIONS Allegation # 1 It is alleged that Officer Elliott worked off-duty on a weekly basis as a Minneapolis Police Officer during 2010 and the beginning of 2011 without submitting the required off-duty application and getting approval to work. If this were found to be true, it would violate the following: 3-801 OFF-DUTY (OUTSIDE) EMPLOYMENT (05/09/2000) In all cases of outside employment for both sworn and civilian employees, the primary duty, obligation, and responsibility of an employee is, at all times, to the MPD. Because the nature of law enforcement requires MPD employees to work irregular duty schedules, and certain occupations inherently conflict with an employee's primary responsibility to the MPD, the MPD may impose restrictions on outside employment. All MPD employees who wish to work off-duty/outside employment shall receive prior approval through the application process before the off-duty employment commences. Investigative Facts • Visinet Records show that Officer Elliott worked off-duty 4- 5 times a month during 2010 and 2011 on various days throughout the week • Officer Elliott admitted he works off-duty at 13.43 - Personnel Data 13.43 - Personnel Data • Officer Elliott admitted he had been working off-duty for more than a year without approval • Officer Elliott said he forgot to submit an off-duty request form • Workforce Director shows that Officer Elliott did not submit an off-duty application from 2005-2010 to get approval to work 4 1212222 • Workforce Director shows that Officer Elliott did not submit an off-duty application until March 2011 and it was rejected • Officer Elliott was sent a notification letter to give a Garrity Statement regarding his Off-Duty employment on May 19, 2011 • Officer Elliott submitted an off-duty request to work at 2011 and was approved • Officer Elliott never submitted an off-duty request to work at 13.43 - Personnel Data 13.43 Respectfully Submitted, ..) Sgt. Melissa Chiodo Internal Affairs Unit 13.43 - Personnel Data 5 1212223 | C857: ['https://d3n8a8pro7vhmx.cloudfront.net/cuapb/pages/1461/attachments/original/1638089363/13-30577_Elliott.pdf?1638089363'] | D857: ['David C. Elliott, badge #1755'] | E857: ['Department:Minneapolis Police Department'] | F857: 8064 | K857: =IF(Final_Cleaned_Data_V2!J857="Other", "Please specify here", "") | N857: =IF(Final_Cleaned_Data_V2!M857="Other", "Please specify here", "")
A858: 937 | B858: Minneapolis City of Lakes Police Department Timothy J. Dolan Chief of Police 350 South 5th Street - Room 130 Minneapolis MN 55415-1389 Office 612 673-2853 TTY 612 673-2157 Officer John Chamberlain License Investigation Minneapolis Police Department March 8, 2012 RE: IAU Case Number #11-199 Notice of Suspension (10 hours suspension without pay) Officer Chamberlain, The finding for IAU Case #11-199 is as follows: MPD P/P 5-103 Use of Discretion...SUSTAINED (Category B) MPD P/P 5-105 Professional Code of Conduct (9)...SUSTAINED (Category B) MPD P/P 5-105 Professional Code of Conduct (10, (14), (15)...SUSTAINED (Category B) As discipline for this incident you are suspended for 10 hours without pay. This case will remain a "B" violation and will remain on file until 12/04/2014, which is three years from the date of incident. This case will remain in IAU files per the record retention guidelines mandated by State Law. Be advised that any additional violations of Department Rules and Regulations may result in more severe disciplinary action up to and including discharge from employment. Sincerely, Timothy J. Dolan Chief of Police By: Janee Harteau Assistant Chief City Information and Serv,ces www.ci.minneapolis.mn.us Affirmative Action Employer 1228066 Page 2 Officer John Chamberlain Suspension Letter I, Officer John Chamberlain, acknowledge receipt of this Notice of Suspension. (Ire-cer John Chamberlain TJD:mar CC: Personnel IAU - 7-.26i-a • Date of Receipt 1228065 From: Adams, Charlie F. Sent: Monday, December 12, 2011 12:49 AM To: Arneson, Kristine Cc: Halvorson, Henry Subject: Officer John Chamberlain Inspector Arneson, Today 12/12/11, I received a complaint from Officers 13.43 - Person 13.43 about Officer Chamberlain behavior on a recent arrest. The two officers were dealing with an underage female for consumption. The female had assaulted an employee at Epic Night Club. Officers had taken the female into custody and place her in the rear of squad 112 P # 76406. The officers requested a PBT to their location, so they could test the female. Officer Chamberlain arrives with the PBT and he attempts to test the female. The female refused to take the test. Officers 13.43 - Person 13.43 were in the front of the squad filing out paper work for the arrest, when Officer Chamberlain got into the rear of the squad and began forcing the female to blow into the PBT. Officers 13.43 - Person 13.43 said that Officer Chamberlain was lying on top of the handcuffed female forcing the unit to her mouth. Once he got the reading her got off her and came out of the squad. I viewed the squad video and I saw the female refuse the test and she asked for as lawyer a couple of times. There was also some bad language used but what concerned me more was Officer Chamberlain forcing himself on the female. Both Officers 13.43 - Persor 13.43 were mainly concerned about Officer Chamberlain forcing himself on the female too. Officer 13.43 - Person 13.43 were nervous about reporting this but they felt the female might take legal action and make a complaint due to Officer Chamberlains conduct. I would like IAU to take a look at the video for any department violations or not. The case number for this arrest is 11- 362304 and date of arrest is 12/04/2011 at 0106 hours. To review the squad video the date is 12/04/2011 and the squad P number is 76406 and the time of the video is 01:16:26 and the time of the incident is at 01:25:09. The arrested female name is 13.43 - Personnel Data 1228067 Sgt. C. F Adams #0009 1St Precinct Middle Watch 1228068 MINNEAPOLIS POLICE DEPARTMENT Internal Affairs Unit IAU Administrative Case #11-199 Sergeant Jon Hoff CASE BACKGROUND This case was assigned 12-13-11 as the result of an e-mail sent from Inspector Arneson to Lt. Glampe requesting that someone from IAU look into an incident that involved First Precinct Officer John Chamberlain (tab #3). This is related to MPD CCN: 11-362304 (tab#12) SUMMARY OF ALLEGATIONS It is alleged that Officer Chamberlain: • Pushed a handcuffed female to her side and laid on her. • Forced a female to take a PBT after she refused. • Used derogatory and indecorous language. • Refused to give his name upon request. If these allegations are found to be true it would violate the following department policy(s) (tab #16): 5-103 Use of Discretion: The police profession is one that requires officers to use considerable judgment and discretion in the performance of their daily duties. Officers have a large body of knowledge from Department policies and procedures, training, their own professional police experience and the experiences of their fellow officers to guide them in exercising proper judgment and discretion in situations not specifically addressed by Department rules and regulations. In addition, officers must always adhere to the following principles in the course of their employment with the Minneapolis Police Department: • POLICE ACTION - LEGALLY JUSTIFIED: Officers must act within the limits of their authority as defined by law and judicial interpretation, thereby ensuring that the constitutional rights of individuals and the public are protected. • EQUALITY OF ENFORCEMENT: Officers shall provide fair and impartial law enforcement to all citizens. 1 1228069 LOYALTY: Officers shall be faithful to their oath of office, strive to uphold the principles of professional police service, and advance the mission of the Department. 5-105 Professional Code of Conduct (9), (10), (14), (15): • Employees shall give their name and/or badge number to any person upon request. • Employees shall not use indecent, profane or unnecessarily harsh language in the performance of official duties or in the presence of the public. • Employees shall not use any derogatory language or actions which are intended to embarrass, humiliate, or shame a person, or do anything intended to incite another to violence. • Employees shall be decorous in their language and conduct. They shall refrain from actions or words that bring discredit to the Department. They shall also not use words or terms which hold any person, group or organization up to contempt. The use of such unacceptable terms is strictly forbidden. CASE INVESTIGATION CAPRS On 12-04-11 Officers 13.43 - Persoi 13.43 were assigned to squad 112 and were flagged down at approximately 0115 in front of the Epic Night Club located at 110 N 5th St on a report of an assault. Officers took the listed AP in custody, placed her in handcuffs, and then in the rear of their car. Officers could smell the odor of an alcoholic beverage coming from AP and she was determined to be under the legal drinking age of 21. They requested a PBT to their location and Officer Chamberlain who was assigned to Squad 122 arrived to assist. AP registered a positive test sample which indicated alcoholic beverage consumption. AP was booked HCJ by the Booking Van 149 for Assault 5 and Minor Consumption (tab#12) Summa of Supplement #1 (Officer Officer 13.43 was assigned to Squad 112 with Officer 13.43 when they were flagged down on an assault at the Epic Nightclub. They took the listed AP into custody, placed her in handcuffs, and then in the rear of their squad. He could smell the odor of an alcoholic beverage coming from AP. AP continually elled at the bouncers of the nightclub and at others who were in the area. Officer 13.43 asked for a squad with a PBT to come to his location and Officer Chamberlain arrived. Officer Chamberlain advised that AP had registered alcohol in her system. 1 .43 13.4 13.43 Summa of Supplement #2 (Office Officer 13.43 was assigned to Squad 112 with Officer 13.43 when they were flagged down by bouncers from the Epic Nightclub. The bouncers were holding a female (AP) who was struggling to get free. Officer 13.43 handcuffed AP and placed in the rear of the squad. It was determined that AP had assaulted one of the bouncers. 2 1228070 | C858: ['https://d3n8a8pro7vhmx.cloudfront.net/cuapb/pages/1461/attachments/original/1638080340/13-31064_Chamberlain_Part_1.pdf?1638080340'] | D858: ['John Chamberlain, badge #1075'] | E858: ['Department:Minneapolis Police Department'] | F858: 8079 | K858: =IF(Final_Cleaned_Data_V2!J858="Other", "Please specify here", "") | N858: =IF(Final_Cleaned_Data_V2!M858="Other", "Please specify here", "")
A859: 938 | B859: 3/16/2021 New Minneapolis Fourth Precinct inspector's story is one of the North Side - StarTribune.com https://www.startribune.com/new-minneapolis-fourth-precinct-inspector-s-story-is-one-of-the-north-side/600016327/ 1/3 LOCAL New Minneapolis Fourth Precinct inspector's story is one of the North Side Charlie Adams is a product of the area he polices. By Libor Jany, Libor Jany FEBRUARY 1, 2021 - 2:08PM Growing up, Charlie Adams would catch the bus to watch the annual Aquatennial Parade in downtown Minneapolis, where he and his friends used to get stopped and hassled by the police for nothing more than being young and Black. So it came as something of a surprise, then, when he joined the department after college. Fast-forward 35 years, and Adams is the recently appointed inspector of the North Side Fourth Precinct at a crucial moment for policing in the city following the death of George Floyd last May. He steps into the job amid a polarizing debate about the role of law enforcement in American society, with some City Council members and activists arguing that a system with roots in the slave patrols of the Colonial era is inherently racist and therefore cannot be reformed. Adams, 58, agrees the department has to take ownership of past injustices but says he has also seen the difference that good policing can make. The bigger problem, he argues, rests with society at large. "You've got systemic racism in everything," Adams said, using as an example the almost all-white mob attack on the U.S. Capitol that left five people dead earlier this month. "Everyone wants to talk about law enforcement - yes, you know it's there, but it's in our country." Some North Siders say Adams' experience as a Black cop coming up in an often hostile department has prepared Adams to lead a police precinct where racial tensions are perpetually on a low boil. Thick skin is a requirement for any inspector in the Fourth, some say. "I don't see nobody running over him," said Lynne Crockett, a lifelong North Sider who organizes around issues such as education and public safety. "He comes from a whole different bio graphy: He is us, so no one will be able to come up to him and say, 'Well, you don't understand where we're coming from.' " In many ways, Adams' story is the story of the North Side. Like the millions of Southern Blacks who moved north during the Great Migration of the mid-20th century, his family left their home in Arkansas in search of factory jobs and the promise of a more equitable future. They eventually settled in the Sumner Field Homes - the "Old Bricks," as locals called it - one of the many federally funded housing projects that sprang up on the North Side and aggravated racial segregation. Adams grew up playing football with Jerome Benton, who famously played Morris Day's mirror-holding valet in the film "Purple Rain." His father worked as a mechanic, while his mother ran the salad bar at Dayton's for 30 years. After high school, Adams played several years of football at a junior college and after graduating took a variety of odd jobs that included providing security at a department store and "driving the last No. 21 bus out of downtown St. Paul every night." He said the job with Metro Transit was the best training for becoming a cop because it taught him how to deal with people of diverse backgrounds using nothing but his wits. ANTHONY SOUFFLE • STAR TRIBUNE As a kid, Charlie Adams spent time at The Way, a North Side community center, now the site of Minneapolis' Fourth Precinct station. Some 3/16/2021 New Minneapolis Fourth Precinct inspector's story is one of the North Side - StarTribune.com https://www.startribune.com/new-minneapolis-fourth-precinct-inspector-s-story-is-one-of-the-north-side/600016327/ 2/3 He applied to the MPD on a whim, telling himself that the best way to change a system was from within. He almost quit when he had a racist run-in with a white supervisor a few months into the police academy, but decided to stick it out after being reassigned to another Black officer, Gerald Moore, who took him under his wing. Adams said he had many mentors over the years, both inside the department and out, including the late Ron Edwards (https://www.startribune.com/longtime-minneapolis- civil-rights-activist-ron-edwards-dies-at-81/567175332/) , a titan of the local civil rights movement who advocated for diversifying the city's police and fire departments. Taking a cue from Edwards, Adams became an outspoken advocate for diversifying the department, which then was even more overwhelmingly white and male than it is today. He was one of five Black officers - a group that included the current chief Medaria Arradondo and was known as "The Mill City 5" - who sued the department (https://www.startribune.com/high-ranking-black-cops-sue-minneapolis-police- department/12081986/) in 2007 over allegations that Blacks on the force were subjected to a hostile work environment and disparate treatment since the late 1980s. The officers settled with the city out of court for $740,000. Like others who look like him and wear the uniform, Adams says he has always walked a tightrope. As a Black man, he said he was disturbed by the sight of Floyd's death under the knee of a since-fired city officer and other recent high-profile incidents across the city. But he said that for all of its ills, he still sees policing as a noble calling. Police, he says, are often the only ones available to respond quickly to emergencies in high-crime neighborhoods that have been failed over and over again by governmental and societal institutions. That puts him at odds with a new generation of activists who argue that failed efforts to change the culture within the department prove that it's beyond reform. Some, including several City Council members, have even called for its abolishment, in favor of a new system of public safety that will prioritize the safety of all residents. Adams said that he intends to work closely with council members Jeremiah Ellison and Phillipe Cunningham, whose wards cover much of north Minneapolis and who have been among loudest critics of the MPD. But he said his top priority is to the residents in the precinct, who share with him their complaints about drug deals, drive-by shootings and speeding traffic. "I really don't care what the other people say about defunding the policing or demolish the police unless it's people that live in this neighborhood, right?" he said. "They're the bosses, right?" Ellison said that despite his past criticism of the department, he had a strong relationship with Adams' predecessors and said one of Adams' biggest challenges will be to begin undoing the harm done by decades of overaggressive policing. "You're also inheriting a lot of bad will and so there's a lot of work that's needed there to build there," Ellison said. Despite the area's reputation, he said he believes many North Siders having a begrudging respect for police, a perception reinforced by the fact that the area escaped much of the arson and destruction that engulfed parts of the South Side after Floyd's death. He long ago moved from the North Side to a northern suburb, but Adams still spends many of his off-duty hours there. For the past several years, he has served as a defensive coordinator for the powerful North High football team, coached by his son, Charles. Still, he faces a tall challenge in taking over the Fourth Precinct, which has been a revolving door in recent years. Violent crime is a constant problem, and he will also have to motivate street cops who in the past felt abandoned by department leadership during controversies. 3/16/2021 New Minneapolis Fourth Precinct inspector's story is one of the North Side - StarTribune.com https://www.startribune.com/new-minneapolis-fourth-precinct-inspector-s-story-is-one-of-the-north-side/600016327/ 3/3 "Like I tell all my guys, I'm gonna support you, I'm gonna fight for you; you know if there's a mistake, then we need to know right away so that we can work on that," he said. Libor Jany • 612-673-4064 Twitter: @StribJany | C859: ["https://d3n8a8pro7vhmx.cloudfront.net/cuapb/pages/270/attachments/original/1615987082/2021Adams_New_Minneapolis_Fourth_Precinct_inspector's_story_is_one_of_the_North_Side.pdf?1615987082"] | D859: ['Charles F. Adams, badge #9'] | E859: ['Department:Minneapolis Police Department'] | F859: 8106 | K859: =IF(Final_Cleaned_Data_V2!J859="Other", "Please specify here", "") | N859: =IF(Final_Cleaned_Data_V2!M859="Other", "Please specify here", "")
A860: 939 | B860: Screen-shot post C: KMSP .10140t11224619MAA Alicia Lucio You say "Finally" like you are praising the murder rate. Sigh Yesterday at 5:35 PM Like in 9;92 7.SrP • Wm\ • ■ 11, 0 • 414 ( 110.'' ,) 7 Officer Klimmek's explanation of screen-shot C was, "She said...Yeah, she said, umm, like I was praising the murder rate and I was not praising the murder rate. She can think whatever she wants and say it, but that doesn't mean that's what my thoughts are." Officer Klimmek reported that Ms. Lucio had access to all his posts on Facebook, as she was a friend. 7 1208906 Screen-shot Post D: I_.= 1112e4 VIN,P1014031121409/WAA r.. I I Joseph Klimax Last few years were slow. Yesterday at 5:34 PM Like Alida Lucio Officer Klimmek reported the following explanation of screen-shot D, "Just that it's been slow. Like I said earlier, it's been slow the last couple of years and cops like to be busy, you know, not sitting at the station. Officer Klimmek reported, "I was stating that the last couple of years have been slow, umm, for work, but you know, I didn't say, "the last few years were slow in murders," or anything like that, so l wasn't even talking about murders at all, just that work's been slow." 8 1208907 Screen-shot Post E: PAP 201403111/4659/57M Timeline 13.43 Joseph Klimax Saturday at 8:08 PM via iOS If your husband isn't always there. -S4 Officer Klimmek reported that the phrase, "if your husband isn't always there" refers to another picture, screen-shot F. 9 1208908 Screen-shot post F: 1.0 , '444 In screen-shot post F, Officer Klimmek reported that he "shared" this image after he viewed it on Facebook. He stated he did not create the image. He reported, "The word is "Ghetto Hot, Red Hot," which I believe is some website. And the picture is of white stick figure behind bars with a white female stick figure and then a bunch of small children stick figures that are white and then a white dog." Moreover, I asked the following follow-up questions and Officer Klimmek provide the following responses: 0: Could you characterize how long you looked at this particular posting in post "F" and shared it? Did you contemplate it for days and weeks, or was it something that you did pretty quickly? A: Well, probably something I did pretty quickly. Yeah. Q: Did you intend for this sharing of this posting "F" to be inflammatory or demeaning or derogatory, or can you explain what your feelings were there? A: No, I didn't mean it to be demeaning or derogatory, but umm, it's just, you know, it's just humorous in the fact that, umm, whoever put that picture up, it's humorous that when your husband can't be there if he's in a prison. So, umm, that's, it was all in a sense of humor, not...umm... Q: Is that your characterization here, that this stick figure as you stated behind bars, is in prison? A: Or in jail. But I don't know, I didn't make that, I just shared it. 10 1208909 Post G: PAM, ,X11.11.1 11,410/5/AA FOX 9 9:03 37" 4. 9. 00 Sprint 12:18AM (Pd S100%011101 Timeline th ill Joseph Kilmnx Fixed. ("Th III 44 4 Officer Klimmek described screen shot post G, that he shared in his Facebook account, "It's just, you know, it's just in the North Side there's a lot of crime, a lot of people are jailed, it's the city's most busiest crime ridden part of the city and a lot of people are now in jail, so, it's just a little humorous look at the situation I would say. It wasn't meant to be inflammatory. Obviously I'm not gonna have a bunch of friends on Face Book, and you're gonna be inflammatory for very long before you won't have any more friends on Face Book. Well, it's just three white figure...stick figures behind bars and one female white stick figure, some child white stick figures, and a white dog stick figure." 11 1208910 Screen-shot post H: to LFALgre...11abi Officer Klimmek provided an explanation of screen-shot post H, "This was posted before, this is probably one of the first postings, so it was not as...uh, shot at anyone who is Hispanic, this was posted well before that. Umm...But what happened is this is filed as a court case in California. It says, "Just got my new Cinco de Mayo shirt. Hey California, (inaudible)," which means "come get them." Moreover, "what it pertains to is in California they have a very...they have a hard situation in schools where during Cinco de Mayo they believe that wearing American flag shirts or the American flag in itself was inflammatory and could erupt in violence in the school during Cinco de Mayo. So the school banned the flag - the American flag and American flag shirts - because it could cause violence. I put on this post and I said that I felt that I have no problem with Cinco de Mayo, however, if there's an event that is so dangerous and so volatile that wearing an American flag shirt in America - that maybe the event should be curbed. Not people, or...The event should be curbed, rather than people's first amendment rights. You know, I fought...1 went to Afghanistan, defended the flag, I had friends who came back in coffins with the flag draped over them, so I think the American flag and free speech trumps an event - a party. So and that's why I put that on there. And that's what that was about. And I shared that picture, so I didn't make that." 12 1208911 When asked how images and information about him were posted and available on the "open web source," Officer Klimmek stated that his friend Alicia Lucio posted or tagged his photos on her Facebook account. Officer Klimmek reported he did not intend for his Facebook postings to be public. He offered the following characterization of his postings, "I believe that the pictures are humorous. None of those pictures had intent of demeaning anyone or inflammatory at all, you know, and they're for my friends, so you know, obviously we don't all have the same sense of humor and my friends, if they shared, you know, and these (inaudible)...l...they...I add them or they add me, they're on my Face Book they have the same sense of humor and uh, and they're okay with it, so." I asked the following follow-up questions and I was provided with the following answers by Officer Klimmek: 0: I would like to show you also what's out there on open source. For example; news stories. There's one by KMSP, Fox 9, based on the video. There's another one by Insight News.com, based on the video - different authors. And there's one on Raw Story.com, in addition to other stories that are posted on open source as a result of this video. Are you aware of those also? A: Uhh...l have looked at them. Q: In your postings using the name of Joseph Klimax, K-L-I-M-A-X, can you tell me if you were conducting yourself based on the screen shots, based on the video, in a professional and ethical manner based on the screen shots "A" through "H" that displayed and played on the video? A: I believe that the pictures are humorous. None of those pictures had intent of demeaning anyone or inflammatory at all, you know, and they're for my friends, so you know, obviously we don't all have the same sense of humor and my friends, if they shared, you know, and these (inaudible)...I...they...1 add them or they add me, they're on my Face Book they have the same sense of humor and uh, and they're okay with it, so. 0: In your postings using the name of Joseph Klimax, can you tell me if you offended the professional and ethical standards of the Minneapolis Police Department based on screen shots "A" through "H" that I've displayed to you and based on the video? A: You know, I...You know, I think someone can find offense in everything. Umm...I don't think they were offensive. I thought, uh, you know, people would get a laugh out of them, it would be a little humorous, and uh, and the one about being busy, like I said, just like a firefighter wants to fight fires, cops want to fight crime, so it's you know, not glorifying murders at all, it's just saying that cops like to be busy out with the public and I think the public wants cops to be busy vs. being at the station doing nothing. 13 1208912 | C860: ['https://d3n8a8pro7vhmx.cloudfront.net/cuapb/pages/1461/attachments/original/1638148305/14-05557_Klimmek_Part_2.pdf?1638148305'] | D860: ['Joseph Klimmek, badge #3735'] | E860: ['Department:Minneapolis Police Department'] | F860: 8193 | K860: =IF(Final_Cleaned_Data_V2!J860="Other", "Please specify here", "") | N860: =IF(Final_Cleaned_Data_V2!M860="Other", "Please specify here", "")
A861: 940 | B861: Name of Plaintiff Liability Payout Incident Date Type Year Case Resolved Trial, Court Order or Settled 2009 CITY PREVAILED Don Newcom Conley 4/19/2001 OC 2009 Court Order Rickey Jones 11/22/2002 OC 2009 Trial Rickey Dukes 7/31/2003 OC 2009 Court Order Alfred Flowers 7/15/2004 OC 2009 Court Order Carter Jr., Herbert Louis 12/7/2004 OC 2009 Court Order Quincy Smith 7/13/2005 OC 2009 Court Order Anthony Ray Spann 1/13/2006 OC 2009 Trial Kenneth Bady 2/24/2006 OC 2009 Trial Timothy Jones 03/18/07 OC 2009 Court Order Dan Romig 10/30/2007 OC 2009 Court Order LIABILITY PAYOUTS Symone Taylor $15,000.00 2/3/2006 OC 2009 Settled Nancy Johnson $65,000.00 8/4/2006 OC 2009 Settled Derrick Simmons $35,000.00 8/4/2006 OC 2009 Settled Gianna Madison $999.99 08/06/2007 OC 2009 Settled Otieno & Wong Walton $169,500.00 9/2/2007 OC 2009 Settled Clarence Johnson $201.00 11/14/2007 OC 2009 Settled Eldridge Chatman $495,000.00 4/11/2008 OC 2009 Settled 2010 CITY PREVAILED Falodun, Bright & Irwin, Casey 4/21/2001 OC 2010 Court Order Mahaffy, Jackson & Flora, Daniel 5/14/2004 OC 2010 Court Order Jane Doe 7/14/2004 OC 2010 Court Order Neng Por Yang 11/8/2004 OC 2010 Court Order Denise Kolhoff 10/11/2005 OC 2010 Trial Corvin Bolden v. Beaupre 3/24/2006 OC 2010 Trial Randy Philip Rau 4/11/2006 OC 2010 Court Order Malik Al-Mustafa El-Alamin 4/17/2006 OC 2010 Court Order Michael Scott Undlin 6/9/2006 OC 2010 Court Order Fong Lee 7/22/2006 OC 2010 Trial Steven Mogol 8/13/2006 OC 2010 Court Order Victoria Johnson 12/20/2006 OC 2010 Court Order Edwin Ombuya Okongo 3/22/2008 OC 2010 Court Order Valerui Zamfir 6/4/2008 OC 2010 Court Order Alfred Flowers 1/21/2009 OC 2010 Trial Peter Rickmyer 5/5/2009 OC 2010 Court Order Andre Anthony Riley 8/26/2009 OC 2010 Court Order Marcell Scott 9/17/2009 OC 2010 Court Order Kris Alan Hahn v. Bauer, et al - OC 2010 Court Order LIABILITY PAYOUTS Rickey Jones $15,000.00 11/7/2002 OC 2010 Settled Anthony Ricci $21,500.00 2/6/2004 OC 2010 Settled Sherod Jones $3,000.00 11/23/2004 OC 2010 Settled Jessica Baribeau, et al. $165,000.00 7/22/2006 OC 2010 Settled Minneapolis Police Department "Officer Conduct" Lawsuits Resolved Between 2009 and 9/30/2013 City Prevailed: 10 2009 Total Officer Conduct Lawsuits Resolved: 17 Liability Payouts: 7 City Prevailed: 19 "City Prevailed" includes dismissal by court order as a result of City motion to dismiss or verdict for City or officer(s) at trial. "Liability Payouts" includes settlements or verdict for Plaintiff at trial. Name of Plaintiff Liability Payout Incident Date Type Year Case Resolved Trial, Court Order or Settled Minneapolis Police Department "Officer Conduct" Lawsuits Resolved Between 2009 and 9/30/2013 "City Prevailed" includes dismissal by court order as a result of City motion to dismiss or verdict for City or officer(s) at trial. "Liability Payouts" includes settlements or verdict for Plaintiff at trial. Terry Williams $3,000.00 7/26/2006 OC 2010 Settled John Gardner $150.00 7/27/2006 OC 2010 Settled Augustin Ganley $70,800.00 8/31/2007 OC 2010 Settled Latora Powers $10,000.00 9/11/2007 OC 2010 Settled Sherrie Williams $200.00 10/17/2008 OC 2010 Settled Nicholas Kastner $75,000.00 12/11/2008 OC 2010 Settled Derryl Jenkins $235,000.00 2/19/2009 OC 2010 Settled Rolando Ruiz $120,066.37 4/30/2009 OC 2010 Settled Liability Payouts: 12 2011 CITY PREVAILED Devon Seivers 9/9/2006 OC 2011 Trial Dwight Young 5/10/2007 OC 2011 Trial Timothy Galarnyk 8/2/2007 OC 2011 Court Order Paul Stepnes 5/28/2008 OC 2011 Court Order Esther Brown 8/27/2009 OC 2011 Court Order Hollie Jane Olson 8/27/2009 OC 2011 Trial Nokomis Enterprise (CedarQuickstop) 6/28/2010 OC 2011 Court Order LIABILITY PAYOUTS John Wuchko $40,000.00 5/30/2003 OC 2011 Settled Alicia Smith $4,500.00 9/17/2004 OC 2011 Settled Malcom Labon $45,000.00 8/8/2006 OC 2011 Settled Katie Felder (Dominic) $2,189,128.66 9/21/2007 OC 2011 Trial Herr v. Peterson, et al. $3,000.00 10/4/2007 OC 2011 Settled Jermaine Reed $20,000.00 12/17/2007 OC 2011 Settled Mark Kallenbach $17,500.00 9/1/2008 OC 2011 Settled Tenise Winder $190,000.00 9/3/2008 OC 2011 Settled Max Graves $90,000.00 10/4/2008 OC 2011 Settled Nicole Madison $296,490.07 12/7/2008 OC 2011 Trial Recardo Meeks $76,500.00 3/25/2009 OC 2011 Settled Zeanna Robinson $35,000.00 4/24/2009 OC 2011 Settled Cassandra Brown $32,830.50 6/16/2009 OC 2011 Settled Darrell Williams $24,500.00 7/10/2009 OC 2011 Settled Rickia Russell $1,000,000.00 2/16/2010 OC 2011 Settled Patricia Knapp $1,500.00 2/26/2010 OC 2011 Settled Thomas Lyons $9,000.00 5/24/2010 OC 2011 Settled 2012 CITY PREVAILED John Powell & D. Evans 11/8/2007 OC 2012 Court Order Rithwan Badel 5/3/2008 OC 2012 Court Order Eldon Bosto 8/17/2011 OC 2012 Court Order Mary Branch 9/30/2007 OC 2012 Court Order Trisha Farkarlun 3/20/2009 OC 2012 Court Order Bill John Dumas 7/22/2008 OC 2012 Court Order Taneka Dortch 1/29/2011 OC 2012 Court Order City Prevailed: 7 Liability Payouts: 17 2011 Total Officer Conduct Lawsuits Resolved: 24 2010 Total Officer Conduct Lawsuits Resolved: 31 Name of Plaintiff Liability Payout Incident Date Type Year Case Resolved Trial, Court Order or Settled Minneapolis Police Department "Officer Conduct" Lawsuits Resolved Between 2009 and 9/30/2013 "City Prevailed" includes dismissal by court order as a result of City motion to dismiss or verdict for City or officer(s) at trial. "Liability Payouts" includes settlements or verdict for Plaintiff at trial. Osman Abukar 4/6/2008 OC 2012 Court Order LIABILITY PAYOUTS Joseph McClennon $5,000.00 12/20/2006 OC 2012 Settled Antoine Lee $68,000.00 3/29/2009 OC 2012 Settled Joseph Elliot $55,000.00 7/23/2009 OC 2012 Settled Ira Stafford $19,578.89 8/14/2009 OC 2012 Settled David Jones $2,500.00 12/7/2009 OC 2012 Settled Fred Farthing $20,000.00 3/4/2010 OC 2012 Settled Nicholas Dahl $8,500.00 6/9/2010 OC 2012 Settled Dorian Hay $6,500.00 10/29/2010 OC 2012 Settled Leah Anderson $30,000.00 3/30/2012 OC 2012 Settled Victoria Johnson $25,000.00 12/20/2006 OC 2012 Settled Demetris Robinson $30,000.00 10/2/2010 OC 2012 Settled Tiffany Crowder $5,500.00 10/10/2012 OC 2012 Settled Bernard Miles $4,500.00 2/13/2009 OC 2012 Settled Tonya Magnan $40,000.00 7/11/2010 OC 2012 Settled Mauricio McKinney $85,000.00 9/13/2011 OC 2012 Settled 2013 YTD 9/30/13 CITY PREVAILED Shakeida Richardson 2/7/2013 OC 2013 Court Order Charles Laliberte 1/23/2007 OC 2013 Court Order Damon Ward 6/17/2011 OC 2013 Court Order Adrian Marr 8/16/2011 OC 2013 Trial Steven Kellum 7/12/2011 OC 2013 Court Order Dorwin Bunyon 5/30/2013 OC 2013 Trial Lee, Anthony 8/12/2011 OC 2013 Trial Mohamed Abdi 2/6/2009 OC 2013 Court Order Bervin Grady 10/26/2010 OC 2013 Trial Diantha Gary 8/21/2010 OC 2013 Trial Brown, Venus 3/30/2010 OC 2013 Court Order LIABILITY PAYOUTS Teflon Edwards 5,000.00 $ 10/16/2008 OC 2013 Settled Albertine Rotimi 6,500.00 $ 8/28/2010 OC 2013 Settled Carl Eller 2,000.00 $ 4/4/2008 OC 2013 Settled Ernest Abbott 70,000.00 $ 11/12/2009 OC 2013 Settled Wayne Newton 10,000.00 $ 7/5/2010 OC 2013 Settled James Keten, et al. 225,000.00 $ 4/13/2011 OC 2013 Settled Martin Schaaron 25,000.00 $ 4/13/2012 OC 2013 Settled Larry Smith 3,075,000.00 $ 9/9/2010 OC 2013 Settled Robinson, Tawana 75,000.00 $ 3/14/2009 OC 2013 Settled Hill, Melissa 999.99 $ 6/9/2011 OC 2013 Settled City Prevailed: 8 YTD 9/30/2013 Total Officer Conduct Lawsuits Resolved: 21 Liability Payouts: 15 2012 Total Officer Conduct Lawsuits Resolved: 23 Liability Payouts: 10 City Prevailed: 11 Name of Plaintiff Liability Payout Incident Date Type Year Case Resolved Trial, Court Order or Settled Minneapolis Police Department "Officer Conduct" Lawsuits Resolved Between 2009 and 9/30/2013 "City Prevailed" includes dismissal by court order as a result of City motion to dismiss or verdict for City or officer(s) at trial. "Liability Payouts" includes settlements or verdict for Plaintiff at trial. Cases Tried: 17 Total Cases Resolved: 116 2009-YTD 9/30/2013 MPD Officer Conduct Lawsuits Resolved City Prevailed Total Cases: 55 Liability Payout Total Cases: 61 | C861: ['https://d3n8a8pro7vhmx.cloudfront.net/cuapb/pages/270/attachments/original/1625772789/John_Wuchko_settlement.pdf?1625772789'] | D861: ['Charles L. Storlie, badge #6908'] | E861: ['Department:Minneapolis Police Department'] | F861: 8202 | K861: =IF(Final_Cleaned_Data_V2!J861="Other", "Please specify here", "") | N861: =IF(Final_Cleaned_Data_V2!M861="Other", "Please specify here", "")
A862: 941 | B862: 4/8/2021 Suit alleges Mpls. police shot Terrance Franklin as he tried to surrender | MPR News https://www.mprnews.org/story/2014/05/09/terrance-franklin-lawsuit 1/3 Suit alleges Mpls. police shot Terrance Franklin as he tried to surrender Brandt Williams Minneapolis May 9, 2014 7:08 p.m. Terrance Franklin, 22, of Minneapolis, shown in an undated family photo. Franklin was shot and killed during an altercation with two Minneapolis police o¨cers on Friday, May 10, 2013. Photo courtesy of Starr Reynolds A civil lawsuit filed in U.S. District Court Friday alleges Minneapolis police officers wrongfully shot and killed 22-year-old Terrance Franklin last year as he tried to surrender. It names as defendants the officers involved, the police chief and city of Minneapolis -- and seeks compensatory and punitive damages of no less than $2 million. According to police accounts, Terrence Franklin was a burglary suspect who -- during a struggle -- grabbed an officer's gun and wounded two officers before police shot and killed him. •Previously: Police describe details of Terrance Franklin shooting The lawsuit offers a very different version of events and accuses the officers of shooting Franklin out of racial bias and anger. It alleges that Franklin, who was 5-10 and weighed 173 pounds, did not forcibly grab an officer's weapon and wound two cops while cornered in the basement of a southwest Minneapolis home on May 10 of last year. Nehemiah Martin, center, holds up a picture of his father, Terrance Franklin, who was last year during an altercation with Minneapolis police o¨cers. At left is Nehemiah's grandmother, Teresa Reynolds, and at right is his mother, Ashley Martin with son Ayden. Elizabeth Dunbar / MPR News, File The officers were so angry by this time, the lawsuit claims, that they killed Franklin quote, "execution style." "We feel very confident that we know exactly what happened in that basement," said Mike Padden, an attorney who represents Franklin's father. Padden said he is basing those allegations partially on the audio from a cellphone video recorded from across the street. •Related: What's really being said on the Terrance Franklin video? The video, shot on a phone by a private citizen, was posted on YouTube shortly after the shooting. MPR News cleaned up some of the background noise out of this version of the audio. However, no gun shots are audible. Padden said he can clearly hear officers using racial slurs and Franklin yelling for them to let him go. "The final, most significant one, 'Don't go putting those hands up now,' was obviously an indication that he had capitulated; his hands were up in the air," Padden said. "That's the kind of thing they would say, meaning, 'why didn't you give up in the beginning,' kind of a thing." 4/8/2021 Suit alleges Mpls. police shot Terrance Franklin as he tried to surrender | MPR News https://www.mprnews.org/story/2014/05/09/terrance-franklin-lawsuit 2/3 Padden said that statement, along with with evidence from the Hennepin County Medical Examiner's report has convinced him that police shot Franklin while trying to surrender. •Previously: Autopsy report: Franklin shot 10 times According to the Medical Examiner, most of the 10 bullets that hit Franklin struck him in the neck and head. Padden alleges that a bullet wound to Franklin's right armpit is proof the young man had his hands up in a surrender position when he was shot. A Hennepin County Grand Jury empanelled last fall did not bring criminal charges against officers Lucas Peterson and Michael Meath, who fired their weapons. Meath and another officer, Ricardo Muro, were wounded during the confrontation. Minneapolis police chief Janee Harteau declined to comment on the lawsuit, but released a written statement saying the department has provided extensive evidence to support the officer's claims. "I continue to fully support the actions of my officers and agree with the decision of the Grand Jury," Harteau wrote. Sgt. John Delmonico, president of the Minneapolis Police Federation, said Franklin gave the officers no other choice but to use lethal force. "He chose to take an officer's gun and shoot two cops," Delmonico said. " He is a criminal. He made the decisions that led to his demise that day. And these cops are the heroes in this story." Delmonico calls the lawsuit allegations quote, 'crazy.' He also challenges its claim that Franklin's death was the result of a culture of racism and brutality within the police department. "I don't think there's this culture," Delmonico said. "I think cops do an outstanding job. And to the people who disagree with me, if cops aren't getting hung at noon on Hennepin Avenue, then justice isn't being served." Padden and other critics of the police department say police and city leaders aren't doing enough to reduce the amount of payouts in officer misconduct litigation. An MPR News analysis of data provided by the Minneapolis City Attorney's Office found that since 2003 the city has paid out more than $21 million in officer conduct-related lawsuit settlements, judgments and claims. The payouts involve incidents which occurred as far back as 1992. The Franklin shooting led to protests in which demonstrators called for an independent investigation by an outside agency, such as the FBI. Padden claims an outside investigator would have done a better job in this case. In the complaint, he wrote that, Minneapolis police ignored the video, "because they knew or should have known that their SWAT members could be heard multiple times using the word 'nigger' and therefore, they did not want to take the PR hit with audio enhancement confirming use of that word." He said the department neglected to check for residue on Franklin's hands that would have shown if he had fired a gun. Padden claims Minneapolis police also erred in not promptly interviewing officers Peterson, Meath and Muro. According to the complaint, investigators interviewed Peterson four days after the shooting, Meath two weeks later and Muro nearly three weeks later. However, Delmonico said that's not usual. Noting that Meath and Muro were taking pain medication because of their injuries, he said, "I would argue they were not in the best shape to give a statement." Delmonico also said some experts say sometimes a person's memory is best a few days after a traumatic incident. Late last year, Harteau announced a plan to have the state Bureau of Criminal Apprehension investigate incidents of Minneapolis officers killing civilians. However, that plan was scuttled by Gov. Mark Dayton. MPR News examined a series of emails and documents sent between the department of Public Safety and the police department which showed the police union also opposed the plan. Union officials oppose having officer's statements recorded -- which is standard practice in BCA investigations. Read the complaint: 4/8/2021 Suit alleges Mpls. police shot Terrance Franklin as he tried to surrender | MPR News https://www.mprnews.org/story/2014/05/09/terrance-franklin-lawsuit 3/3 Your support matters. You make MPR News possible. Individual donations are behind the clarity in coverage from our reporters across the state, stories that connect us, and conversations that provide perspectives. Help ensure MPR remains a resource that brings Minnesotans together. Donate today. A gift of $17 makes a difference. Support MPR News UNITED STATES DISTRICT CO DISTRICT OF MINNESOTA Walter Louis Franklin, II, Trustee For the Estate of Terrance Terrell Franklin, Plaintiff, v. LUCAS PETERSON individually, and in his official capacity; MICHAEL MEATH, individually, and in his official capacity; JANEÉ HARTEAU, Chief of Police for the Minneapolis Police Department, individually and in her official capacity; and the CITY OF MINNEAPOLIS, Defendants. ) ) ) ) ) ) ) ) ) ) ) ) ) ) ) ) ) ) CASE FILE N COMPLAINT (JURY TRIA To: Defendants above named and their respective attorneys brought pursuant to 42 U.S.C. §§ 1983, and various Am Constitution. The Plaintiff also brings Minnesota common law c pursuant to 2013 Minn. Stat. § 573.02. I. INTRODUCTION CASE 0:14-cv-01467-DWF-JSM Document 2 Filed 1  of 24  © 2021 Minnesota Public Radio. All rights reserved. | C862: ['https://d3n8a8pro7vhmx.cloudfront.net/cuapb/pages/270/attachments/original/1617896979/Suit_alleges_Mpls._police_shot_Terrance_Franklin_as_he_tried_to_surrender___MPR_News.pdf?1617896979'] | D862: ['Andrew Stender, badge #6791', 'Lucas Peterson, badge #5630', 'Mark Durand, badge #1627', 'Michael Meath, badge #4686', 'Ricardo Muro, badge #4899'] | E862: ['Department:Minneapolis Police Department'] | F862: 8233 | K862: =IF(Final_Cleaned_Data_V2!J862="Other", "Please specify here", "") | N862: =IF(Final_Cleaned_Data_V2!M862="Other", "Please specify here", "")
